{
  "templateName": "JLC06121H-3313",
  "showName": "JLC06121H-3313",
  "stencilLayer": 6,
  "stencilPly": 1.2,
  "cuprumThickness": 1,
  "insideCuprumThickness": 0.5,
  "defaultFlag": false,
  "expeditedFlag": true,
  "enableFlag": true,
  "sort": 2,
  "fixedFee": 0,
  "coefficient": 0,
  "iaminationList": [
    {
      "content": "{\u0022LineLayer\u0022:\u0022Layer\u0022,\u0022lineMaterialType\u0022:\u0022Copper\u0022,\u0022LineThickness\u0022:\u00220.035mm\u0022,\u0022coreBoardRemark\u0022:\u0022\u0022}",
      "contentKey": "impedanceContent_115cdd73c8804a11b41a5f8da3acb776",
      "deleteFlag": false,
      "iaminationType": 1,
      "impedanceIaminationAccessId": "115cdd73c8804a11b41a5f8da3acb776",
      "impedanceIaminationKeyId": 355,
      "sort": 0
    },
    {
      "content": "{\u0022preLayer\u0022:\u0022Prepreg\u0022,\u0022preMaterialType\u0022:\u00223313*1\u0022,\u0022preThickness\u0022:\u00220.0994mm\u0022,\u0022coreBoardRemark\u0022:\u0022\u0022}",
      "contentKey": "impedanceContent_3fce37fe77bb48919ecaa111d4b74254",
      "deleteFlag": false,
      "iaminationType": 2,
      "impedanceIaminationAccessId": "3fce37fe77bb48919ecaa111d4b74254",
      "impedanceIaminationKeyId": 356,
      "sort": 1
    },
    {
      "content": "{\u0022coreBoardLayer1\u0022:\u0022inner Layer\u0022,\u0022coreBoardMaterialType1\u0022:\u0022Copper\u0022,\u0022coreBoardThickness1\u0022:\u00220.0152mm\u0022,\u0022coreBoardLayer2\u0022:\u0022Core\u0022,\u0022coreBoardMaterialType2\u0022:\u0022Core\u0022,\u0022coreBoardThickness2\u0022:\u00220.35mm\u0022,\u0022coreBoardLayer3\u0022:\u0022inner Layer\u0022,\u0022coreBoardMaterialType3\u0022:\u0022Copper\u0022,\u0022coreBoardThickness3\u0022:\u00220.0152mm\u0022,\u0022coreBoardRemark\u0022:\u00220.35mm (without copper core)\u0022}",
      "contentKey": "impedanceContent_0a7d865e41554e46b9cbea99eaa176fd",
      "deleteFlag": false,
      "iaminationType": 3,
      "impedanceIaminationAccessId": "0a7d865e41554e46b9cbea99eaa176fd",
      "impedanceIaminationKeyId": 357,
      "sort": 2
    },
    {
      "content": "{\u0022preLayer\u0022:\u0022Prepreg\u0022,\u0022preMaterialType\u0022:\u00222116*1\u0022,\u0022preThickness\u0022:\u00220.1088mm\u0022,\u0022coreBoardRemark\u0022:\u0022\u0022}",
      "contentKey": "impedanceContent_008dbab42703445db49f4127cff53faa",
      "deleteFlag": false,
      "iaminationType": 2,
      "impedanceIaminationAccessId": "008dbab42703445db49f4127cff53faa",
      "impedanceIaminationKeyId": 358,
      "sort": 3
    },
    {
      "content": "{\u0022coreBoardLayer1\u0022:\u0022inner Layer\u0022,\u0022coreBoardMaterialType1\u0022:\u0022Copper\u0022,\u0022coreBoardThickness1\u0022:\u00220.0152mm\u0022,\u0022coreBoardLayer2\u0022:\u0022Core\u0022,\u0022coreBoardMaterialType2\u0022:\u0022Core\u0022,\u0022coreBoardThickness2\u0022:\u00220.35mm\u0022,\u0022coreBoardLayer3\u0022:\u0022inner Layer\u0022,\u0022coreBoardMaterialType3\u0022:\u0022Copper\u0022,\u0022coreBoardThickness3\u0022:\u00220.0152mm\u0022,\u0022coreBoardRemark\u0022:\u00220.35mm (without copper core)\u0022}",
      "contentKey": "impedanceContent_bd474acc409d4651bbdc1ff04151322a",
      "deleteFlag": false,
      "iaminationType": 3,
      "impedanceIaminationAccessId": "bd474acc409d4651bbdc1ff04151322a",
      "impedanceIaminationKeyId": 359,
      "sort": 4
    },
    {
      "content": "{\u0022preLayer\u0022:\u0022Prepreg\u0022,\u0022preMaterialType\u0022:\u00223313*1\u0022,\u0022preThickness\u0022:\u00220.0994mm\u0022,\u0022coreBoardRemark\u0022:\u0022\u0022}",
      "contentKey": "impedanceContent_4caf0bb96aba4533a14ece400d10534f",
      "deleteFlag": false,
      "iaminationType": 2,
      "impedanceIaminationAccessId": "4caf0bb96aba4533a14ece400d10534f",
      "impedanceIaminationKeyId": 360,
      "sort": 5
    },
    {
      "content": "{\u0022LineLayer\u0022:\u0022Layer\u0022,\u0022lineMaterialType\u0022:\u0022Copper\u0022,\u0022LineThickness\u0022:\u00220.035mm\u0022,\u0022coreBoardRemark\u0022:\u0022\u0022}",
      "contentKey": "impedanceContent_d79ac673ca69425b979ebe44d0e0a108",
      "deleteFlag": false,
      "iaminationType": 1,
      "impedanceIaminationAccessId": "d79ac673ca69425b979ebe44d0e0a108",
      "impedanceIaminationKeyId": 391,
      "sort": 6
    }
  ],
  "impedanceTemplateCode": "20211110041935",
  "laminationType": 1,
  "compressionThickness": 1.1384
}