{
  "templateName": "JLC040821-7628",
  "showName": "JLC040821-7628",
  "stencilLayer": 4,
  "stencilPly": 0.8,
  "cuprumThickness": 2,
  "insideCuprumThickness": 1,
  "defaultFlag": false,
  "expeditedFlag": false,
  "enableFlag": true,
  "sort": 1,
  "fixedFee": 0,
  "coefficient": 0,
  "iaminationList": [
    {
      "content": "{\u0022LineLayer\u0022:\u0022Layer\u0022,\u0022lineMaterialType\u0022:\u0022Copper\u0022,\u0022LineThickness\u0022:\u00220.07mm\u0022,\u0022coreBoardRemark\u0022:\u0022\u0022}",
      "contentKey": "impedanceContent_9eb3613ebb824a4482209e2a4a17d0dc",
      "deleteFlag": false,
      "iaminationType": 1,
      "impedanceIaminationAccessId": "9eb3613ebb824a4482209e2a4a17d0dc",
      "impedanceIaminationKeyId": 143,
      "sort": 0
    },
    {
      "content": "{\u0022preLayer\u0022:\u0022Prepreg\u0022,\u0022preMaterialType\u0022:\u00227628*1\u0022,\u0022preThickness\u0022:\u00220.2030mm\u0022,\u0022coreBoardRemark\u0022:\u0022\u0022}",
      "contentKey": "impedanceContent_efb407338de3480fafc3452ec389364e",
      "deleteFlag": false,
      "iaminationType": 2,
      "impedanceIaminationAccessId": "efb407338de3480fafc3452ec389364e",
      "impedanceIaminationKeyId": 144,
      "sort": 2
    },
    {
      "content": "{\u0022coreBoardLayer1\u0022:\u0022inner Layer\u0022,\u0022coreBoardMaterialType1\u0022:\u0022Copper\u0022,\u0022coreBoardThickness1\u0022:\u00220.03mm\u0022,\u0022coreBoardLayer2\u0022:\u0022Core\u0022,\u0022coreBoardMaterialType2\u0022:\u0022Core\u0022,\u0022coreBoardThickness2\u0022:\u00220.2mm\u0022,\u0022coreBoardLayer3\u0022:\u0022inner Layer\u0022,\u0022coreBoardMaterialType3\u0022:\u0022Copper\u0022,\u0022coreBoardThickness3\u0022:\u00220.03mm\u0022,\u0022coreBoardRemark\u0022:\u00220.2mm (without copper core)\u0022}",
      "contentKey": "impedanceContent_2ab71d045e134170b669536bf1df204e",
      "deleteFlag": false,
      "iaminationType": 3,
      "impedanceIaminationAccessId": "2ab71d045e134170b669536bf1df204e",
      "impedanceIaminationKeyId": 145,
      "sort": 3
    },
    {
      "content": "{\u0022preLayer\u0022:\u0022Prepreg\u0022,\u0022preMaterialType\u0022:\u00227628*1\u0022,\u0022preThickness\u0022:\u00220.2030mm\u0022,\u0022coreBoardRemark\u0022:\u0022\u0022}",
      "contentKey": "impedanceContent_74a30ec3a16346dcb32cffd0f7f74e21",
      "deleteFlag": false,
      "iaminationType": 2,
      "impedanceIaminationAccessId": "74a30ec3a16346dcb32cffd0f7f74e21",
      "impedanceIaminationKeyId": 146,
      "sort": 4
    },
    {
      "content": "{\u0022LineLayer\u0022:\u0022Layer\u0022,\u0022lineMaterialType\u0022:\u0022Copper\u0022,\u0022LineThickness\u0022:\u00220.07mm\u0022,\u0022coreBoardRemark\u0022:\u0022\u0022}",
      "contentKey": "impedanceContent_7aaa781b94c64037a961c3808f32ac58",
      "deleteFlag": false,
      "iaminationType": 1,
      "impedanceIaminationAccessId": "7aaa781b94c64037a961c3808f32ac58",
      "impedanceIaminationKeyId": 147,
      "sort": 5
    }
  ],
  "impedanceTemplateCode": "20220617083019",
  "laminationType": 1,
  "compressionThickness": 0.806
}