{
  "templateName": "JLC061611-2116",
  "showName": "JLC061611-2116",
  "stencilLayer": 6,
  "stencilPly": 1.6,
  "cuprumThickness": 1,
  "insideCuprumThickness": 1,
  "defaultFlag": false,
  "expeditedFlag": false,
  "enableFlag": true,
  "sort": 2,
  "fixedFee": 220,
  "coefficient": 55,
  "iaminationList": [
    {
      "content": "{\u0022LineLayer\u0022:\u0022Layer\u0022,\u0022lineMaterialType\u0022:\u0022Copper\u0022,\u0022LineThickness\u0022:\u00220.035mm\u0022,\u0022coreBoardRemark\u0022:\u0022\u0022}",
      "contentKey": "impedanceContent_61aa467b722f441eaebd732175d8c101",
      "deleteFlag": false,
      "iaminationType": 1,
      "impedanceIaminationAccessId": "61aa467b722f441eaebd732175d8c101",
      "impedanceIaminationKeyId": 503,
      "sort": 0
    },
    {
      "content": "{\u0022preLayer\u0022:\u0022Prepreg\u0022,\u0022preMaterialType\u0022:\u00222116*1\u0022,\u0022preThickness\u0022:\u00220.109mm\u0022,\u0022coreBoardRemark\u0022:\u0022\u0022}",
      "contentKey": "impedanceContent_b63779bfc0bf42c2971407746fff305d",
      "deleteFlag": false,
      "iaminationType": 2,
      "impedanceIaminationAccessId": "b63779bfc0bf42c2971407746fff305d",
      "impedanceIaminationKeyId": 504,
      "sort": 1
    },
    {
      "content": "{\u0022coreBoardLayer1\u0022:\u0022inner Layer\u0022,\u0022coreBoardMaterialType1\u0022:\u0022Copper\u0022,\u0022coreBoardThickness1\u0022:\u00220.03mm\u0022,\u0022coreBoardLayer2\u0022:\u0022Core\u0022,\u0022coreBoardMaterialType2\u0022:\u0022Core\u0022,\u0022coreBoardThickness2\u0022:\u00220.50mm\u0022,\u0022coreBoardLayer3\u0022:\u0022inner Layer\u0022,\u0022coreBoardMaterialType3\u0022:\u0022Copper\u0022,\u0022coreBoardThickness3\u0022:\u00220.03mm\u0022,\u0022coreBoardRemark\u0022:\u00220.50mm (without copper core)\u0022}",
      "contentKey": "impedanceContent_61a0befd8253489e889919bfbaea3053",
      "deleteFlag": false,
      "iaminationType": 3,
      "impedanceIaminationAccessId": "61a0befd8253489e889919bfbaea3053",
      "impedanceIaminationKeyId": 505,
      "sort": 2
    },
    {
      "content": "{\u0022preLayer\u0022:\u0022Prepreg\u0022,\u0022preMaterialType\u0022:\u00222116*1\u0022,\u0022preThickness\u0022:\u00220.109mm\u0022,\u0022coreBoardRemark\u0022:\u0022\u0022}",
      "contentKey": "impedanceContent_5af5632acbb2455a99d5b5e8fb755ce4",
      "deleteFlag": false,
      "iaminationType": 2,
      "impedanceIaminationAccessId": "5af5632acbb2455a99d5b5e8fb755ce4",
      "impedanceIaminationKeyId": 506,
      "sort": 3
    },
    {
      "content": "{\u0022preLayer\u0022:\u0022Prepreg\u0022,\u0022preMaterialType\u0022:\u00222116*1\u0022,\u0022preThickness\u0022:\u00220.109mm\u0022,\u0022coreBoardRemark\u0022:\u0022\u0022}",
      "contentKey": "impedanceContent_0ec143c1181e45d983059606fc06d42f",
      "deleteFlag": false,
      "iaminationType": 2,
      "impedanceIaminationAccessId": "0ec143c1181e45d983059606fc06d42f",
      "impedanceIaminationKeyId": 507,
      "sort": 4
    },
    {
      "content": "{\u0022coreBoardLayer1\u0022:\u0022inner Layer\u0022,\u0022coreBoardMaterialType1\u0022:\u0022Copper\u0022,\u0022coreBoardThickness1\u0022:\u00220.03mm\u0022,\u0022coreBoardLayer2\u0022:\u0022Core\u0022,\u0022coreBoardMaterialType2\u0022:\u0022Core\u0022,\u0022coreBoardThickness2\u0022:\u00220.50mm\u0022,\u0022coreBoardLayer3\u0022:\u0022inner Layer\u0022,\u0022coreBoardMaterialType3\u0022:\u0022Copper\u0022,\u0022coreBoardThickness3\u0022:\u00220.03mm\u0022,\u0022coreBoardRemark\u0022:\u00220.50mm (without copper core)\u0022}",
      "contentKey": "impedanceContent_64ad3377661c40a790871e4ff8a37ded",
      "deleteFlag": false,
      "iaminationType": 3,
      "impedanceIaminationAccessId": "64ad3377661c40a790871e4ff8a37ded",
      "impedanceIaminationKeyId": 508,
      "sort": 5
    },
    {
      "content": "{\u0022preLayer\u0022:\u0022Prepreg\u0022,\u0022preMaterialType\u0022:\u00222116*1\u0022,\u0022preThickness\u0022:\u00220.109mm\u0022,\u0022coreBoardRemark\u0022:\u0022\u0022}",
      "contentKey": "impedanceContent_4b94538e2c2a45a8aee2118e953620b8",
      "deleteFlag": false,
      "iaminationType": 2,
      "impedanceIaminationAccessId": "4b94538e2c2a45a8aee2118e953620b8",
      "impedanceIaminationKeyId": 509,
      "sort": 6
    },
    {
      "content": "{\u0022LineLayer\u0022:\u0022Layer\u0022,\u0022lineMaterialType\u0022:\u0022Copper\u0022,\u0022LineThickness\u0022:\u00220.035mm\u0022,\u0022coreBoardRemark\u0022:\u0022\u0022}",
      "contentKey": "impedanceContent_286d3f3e850549efa05243540e65ae4a",
      "deleteFlag": false,
      "iaminationType": 1,
      "impedanceIaminationAccessId": "286d3f3e850549efa05243540e65ae4a",
      "impedanceIaminationKeyId": 510,
      "sort": 7
    }
  ],
  "impedanceTemplateCode": "20220413081539",
  "laminationType": 2,
  "compressionThickness": 1.626
}