{
  "templateName": "JLC080821-1080A",
  "showName": "JLC080821-1080A",
  "stencilLayer": 8,
  "stencilPly": 0.8,
  "cuprumThickness": 2,
  "insideCuprumThickness": 1,
  "defaultFlag": false,
  "expeditedFlag": false,
  "enableFlag": true,
  "sort": 2,
  "fixedFee": 0,
  "coefficient": 0,
  "iaminationList": [
    {
      "content": "{\u0022LineThickness\u0022:\u00220.07mm\u0022,\u0022LineLayer\u0022:\u0022Top Layer\u0022,\u0022lineMaterialType\u0022:\u0022Copper\u0022}",
      "contentKey": "impedanceContent_572c4c9f27c44dddab6a87ef2e00ab73",
      "deleteFlag": false,
      "iaminationType": 1,
      "impedanceIaminationAccessId": null,
      "impedanceIaminationKeyId": 0,
      "sort": 1
    },
    {
      "content": "{\u0022preMaterialType\u0022:\u00221080*1\u0022,\u0022preThickness\u0022:\u00220.071mm\u0022,\u0022preLayer\u0022:\u0022Prepreg\u0022}",
      "contentKey": "impedanceContent_6533985416f84bfe92e99c61826c18c0",
      "deleteFlag": false,
      "iaminationType": 2,
      "impedanceIaminationAccessId": null,
      "impedanceIaminationKeyId": 0,
      "sort": 2
    },
    {
      "content": "{\u0022coreBoardThickness3\u0022:\u00220.03mm\u0022,\u0022coreBoardThickness2\u0022:\u00220.075mm\u0022,\u0022coreBoardLayer1\u0022:\u0022Inner Layer L2\u0022,\u0022coreBoardThickness1\u0022:\u00220.03mm\u0022,\u0022coreBoardRemark\u0022:\u00220.075mm 1/1OZ without copper\u0022,\u0022coreBoardMaterialType1\u0022:\u0022Copper\u0022,\u0022coreBoardMaterialType2\u0022:\u0022Core\u0022,\u0022coreBoardMaterialType3\u0022:\u0022Copper\u0022,\u0022coreBoardLayer2\u0022:\u0022Core\u0022,\u0022coreBoardLayer3\u0022:\u0022Inner Layer L3\u0022}",
      "contentKey": "impedanceContent_734e37c4e8984dfcafe3d48bdccc09fa",
      "deleteFlag": false,
      "iaminationType": 3,
      "impedanceIaminationAccessId": null,
      "impedanceIaminationKeyId": 0,
      "sort": 3
    },
    {
      "content": "{\u0022preMaterialType\u0022:\u0022106*1\u0022,\u0022preThickness\u0022:\u00220.035mm\u0022,\u0022preLayer\u0022:\u0022Prepreg\u0022}",
      "contentKey": "impedanceContent_ac830008e4884c59b52f52a1e811efbc",
      "deleteFlag": false,
      "iaminationType": 2,
      "impedanceIaminationAccessId": null,
      "impedanceIaminationKeyId": 0,
      "sort": 4
    },
    {
      "content": "{\u0022preMaterialType\u0022:\u0022106*1\u0022,\u0022preThickness\u0022:\u00220.035mm\u0022,\u0022preLayer\u0022:\u0022Prepreg\u0022}",
      "contentKey": "impedanceContent_a8e5c5e0c5184619bfcdb3bb179f3d58",
      "deleteFlag": false,
      "iaminationType": 2,
      "impedanceIaminationAccessId": null,
      "impedanceIaminationKeyId": 0,
      "sort": 5
    },
    {
      "content": "{\u0022coreBoardThickness3\u0022:\u00220.03mm\u0022,\u0022coreBoardThickness2\u0022:\u00220.075mm\u0022,\u0022coreBoardLayer1\u0022:\u0022Inner Layer L4\u0022,\u0022coreBoardThickness1\u0022:\u00220.03mm\u0022,\u0022coreBoardRemark\u0022:\u00220.075mm 1/1OZ without copper\u0022,\u0022coreBoardMaterialType1\u0022:\u0022Copper\u0022,\u0022coreBoardMaterialType2\u0022:\u0022Core\u0022,\u0022coreBoardMaterialType3\u0022:\u0022Copper\u0022,\u0022coreBoardLayer2\u0022:\u0022Core\u0022,\u0022coreBoardLayer3\u0022:\u0022Inner Layer L5\u0022}",
      "contentKey": "impedanceContent_b2be80d6dd98407c8c989fc7bd6a017b",
      "deleteFlag": false,
      "iaminationType": 3,
      "impedanceIaminationAccessId": null,
      "impedanceIaminationKeyId": 0,
      "sort": 6
    },
    {
      "content": "{\u0022preMaterialType\u0022:\u0022106*1\u0022,\u0022preThickness\u0022:\u00220.035mm\u0022,\u0022preLayer\u0022:\u0022Prepreg\u0022}",
      "contentKey": "impedanceContent_74d5f658116143fc88e566d32240c605",
      "deleteFlag": false,
      "iaminationType": 2,
      "impedanceIaminationAccessId": null,
      "impedanceIaminationKeyId": 0,
      "sort": 7
    },
    {
      "content": "{\u0022preMaterialType\u0022:\u0022106*1\u0022,\u0022preThickness\u0022:\u00220.035mm\u0022,\u0022preLayer\u0022:\u0022Prepreg\u0022}",
      "contentKey": "impedanceContent_70498a80e98645f8acd9870dd4e8b6c4",
      "deleteFlag": false,
      "iaminationType": 2,
      "impedanceIaminationAccessId": null,
      "impedanceIaminationKeyId": 0,
      "sort": 8
    },
    {
      "content": "{\u0022coreBoardThickness3\u0022:\u00220.03mm\u0022,\u0022coreBoardThickness2\u0022:\u00220.075mm\u0022,\u0022coreBoardLayer1\u0022:\u0022Inner Layer L6\u0022,\u0022coreBoardThickness1\u0022:\u00220.03mm\u0022,\u0022coreBoardRemark\u0022:\u00220.075mm 1/1OZ without copper\u0022,\u0022coreBoardMaterialType1\u0022:\u0022Copper\u0022,\u0022coreBoardMaterialType2\u0022:\u0022Core\u0022,\u0022coreBoardMaterialType3\u0022:\u0022Copper\u0022,\u0022coreBoardLayer2\u0022:\u0022Core\u0022,\u0022coreBoardLayer3\u0022:\u0022Inner Layer L7\u0022}",
      "contentKey": "impedanceContent_81d4461639ef47019c80996abce4701e",
      "deleteFlag": false,
      "iaminationType": 3,
      "impedanceIaminationAccessId": null,
      "impedanceIaminationKeyId": 0,
      "sort": 9
    },
    {
      "content": "{\u0022preMaterialType\u0022:\u00221080*1\u0022,\u0022preThickness\u0022:\u00220.071mm\u0022,\u0022preLayer\u0022:\u0022Prepreg\u0022}",
      "contentKey": "impedanceContent_0b918de84e1943cc9cc2567ac53a78af",
      "deleteFlag": false,
      "iaminationType": 2,
      "impedanceIaminationAccessId": null,
      "impedanceIaminationKeyId": 0,
      "sort": 10
    },
    {
      "content": "{\u0022LineThickness\u0022:\u00220.07mm\u0022,\u0022LineLayer\u0022:\u0022Bottom Layer\u0022,\u0022lineMaterialType\u0022:\u0022Copper\u0022}",
      "contentKey": "impedanceContent_c7f3edd26d3f4ae38f03f1a5cbe3b120",
      "deleteFlag": false,
      "iaminationType": 1,
      "impedanceIaminationAccessId": null,
      "impedanceIaminationKeyId": 0,
      "sort": 11
    }
  ],
  "impedanceTemplateCode": "202309251107181447",
  "laminationType": 2,
  "compressionThickness": 0.827
}