{
  "templateName": "JLC081611-3313",
  "showName": "JLC081611-3313",
  "stencilLayer": 8,
  "stencilPly": 1.6,
  "cuprumThickness": 1,
  "insideCuprumThickness": 1,
  "defaultFlag": false,
  "expeditedFlag": false,
  "enableFlag": true,
  "sort": 4,
  "fixedFee": 330,
  "coefficient": 55,
  "iaminationList": [
    {
      "content": "{\u0022LineThickness\u0022:\u00220.035mm\u0022,\u0022LineLayer\u0022:\u0022Top Layer\u0022,\u0022lineMaterialType\u0022:\u0022Copper\u0022}",
      "contentKey": "impedanceContent_7eb3bf9cc27f40edbd90f8ae4deef8c2",
      "deleteFlag": false,
      "iaminationType": 1,
      "impedanceIaminationAccessId": null,
      "impedanceIaminationKeyId": 0,
      "sort": 1
    },
    {
      "content": "{\u0022preMaterialType\u0022:\u00223313*1\u0022,\u0022preThickness\u0022:\u00220.092mm\u0022,\u0022preLayer\u0022:\u0022Prepreg\u0022}",
      "contentKey": "impedanceContent_bf58c098771841818f5c6937a34ad726",
      "deleteFlag": false,
      "iaminationType": 2,
      "impedanceIaminationAccessId": null,
      "impedanceIaminationKeyId": 0,
      "sort": 2
    },
    {
      "content": "{\u0022coreBoardThickness3\u0022:\u00220.03mm\u0022,\u0022coreBoardThickness2\u0022:\u00220.13mm\u0022,\u0022coreBoardLayer1\u0022:\u0022Inner Layer L2\u0022,\u0022coreBoardThickness1\u0022:\u00220.03mm\u0022,\u0022coreBoardRemark\u0022:\u00220.13mm 1/1OZ without copper\u0022,\u0022coreBoardMaterialType1\u0022:\u0022Copper\u0022,\u0022coreBoardMaterialType2\u0022:\u0022Core\u0022,\u0022coreBoardMaterialType3\u0022:\u0022Copper\u0022,\u0022coreBoardLayer2\u0022:\u0022Core\u0022,\u0022coreBoardLayer3\u0022:\u0022Inner Layer L3\u0022}",
      "contentKey": "impedanceContent_d3d9bf46f9f74801bd38be6f727adfe7",
      "deleteFlag": false,
      "iaminationType": 3,
      "impedanceIaminationAccessId": null,
      "impedanceIaminationKeyId": 0,
      "sort": 3
    },
    {
      "content": "{\u0022preMaterialType\u0022:\u00227628*1\u0022,\u0022preThickness\u0022:\u00220.203mm\u0022,\u0022preLayer\u0022:\u0022Prepreg\u0022}",
      "contentKey": "impedanceContent_88d7b9896362480c9deac4e84ebb9324",
      "deleteFlag": false,
      "iaminationType": 2,
      "impedanceIaminationAccessId": null,
      "impedanceIaminationKeyId": 0,
      "sort": 4
    },
    {
      "content": "{\u0022preMaterialType\u0022:\u00227628*1\u0022,\u0022preThickness\u0022:\u00220.203mm\u0022,\u0022preLayer\u0022:\u0022Prepreg\u0022}",
      "contentKey": "impedanceContent_67f5d975f4ca44418a764600f3bcc6e8",
      "deleteFlag": false,
      "iaminationType": 2,
      "impedanceIaminationAccessId": null,
      "impedanceIaminationKeyId": 0,
      "sort": 5
    },
    {
      "content": "{\u0022coreBoardThickness3\u0022:\u00220.03mm\u0022,\u0022coreBoardThickness2\u0022:\u00220.13mm\u0022,\u0022coreBoardLayer1\u0022:\u0022Inner Layer L4\u0022,\u0022coreBoardThickness1\u0022:\u00220.03mm\u0022,\u0022coreBoardRemark\u0022:\u00220.13mm 1/1OZ without copper\u0022,\u0022coreBoardMaterialType1\u0022:\u0022Copper\u0022,\u0022coreBoardMaterialType2\u0022:\u0022Core\u0022,\u0022coreBoardMaterialType3\u0022:\u0022Copper\u0022,\u0022coreBoardLayer2\u0022:\u0022Core\u0022,\u0022coreBoardLayer3\u0022:\u0022Inner Layer L5\u0022}",
      "contentKey": "impedanceContent_ecb480bdc53441dbb617185296ea20fc",
      "deleteFlag": false,
      "iaminationType": 3,
      "impedanceIaminationAccessId": null,
      "impedanceIaminationKeyId": 0,
      "sort": 6
    },
    {
      "content": "{\u0022preMaterialType\u0022:\u00227628*1\u0022,\u0022preThickness\u0022:\u00220.203mm\u0022,\u0022preLayer\u0022:\u0022Prepreg\u0022}",
      "contentKey": "impedanceContent_dbb727ac10e74b59b06176606cb7b990",
      "deleteFlag": false,
      "iaminationType": 2,
      "impedanceIaminationAccessId": null,
      "impedanceIaminationKeyId": 0,
      "sort": 7
    },
    {
      "content": "{\u0022preMaterialType\u0022:\u00227628*1\u0022,\u0022preThickness\u0022:\u00220.203mm\u0022,\u0022preLayer\u0022:\u0022Prepreg\u0022}",
      "contentKey": "impedanceContent_a21f239dfdfc42a2aca05ede2e7cecd6",
      "deleteFlag": false,
      "iaminationType": 2,
      "impedanceIaminationAccessId": null,
      "impedanceIaminationKeyId": 0,
      "sort": 8
    },
    {
      "content": "{\u0022coreBoardThickness3\u0022:\u00220.03mm\u0022,\u0022coreBoardThickness2\u0022:\u00220.13mm\u0022,\u0022coreBoardLayer1\u0022:\u0022Inner Layer L6\u0022,\u0022coreBoardThickness1\u0022:\u00220.03mm\u0022,\u0022coreBoardRemark\u0022:\u00220.13mm 1/1OZ without copper\u0022,\u0022coreBoardMaterialType1\u0022:\u0022Copper\u0022,\u0022coreBoardMaterialType2\u0022:\u0022Core\u0022,\u0022coreBoardMaterialType3\u0022:\u0022Copper\u0022,\u0022coreBoardLayer2\u0022:\u0022Core\u0022,\u0022coreBoardLayer3\u0022:\u0022Inner Layer L7\u0022}",
      "contentKey": "impedanceContent_17d81047549b40f08178654ff6eefe30",
      "deleteFlag": false,
      "iaminationType": 3,
      "impedanceIaminationAccessId": null,
      "impedanceIaminationKeyId": 0,
      "sort": 9
    },
    {
      "content": "{\u0022preMaterialType\u0022:\u00223313*1\u0022,\u0022preThickness\u0022:\u00220.092mm\u0022,\u0022preLayer\u0022:\u0022Prepreg\u0022}",
      "contentKey": "impedanceContent_4451b598c02241429df29b1348189a3a",
      "deleteFlag": false,
      "iaminationType": 2,
      "impedanceIaminationAccessId": null,
      "impedanceIaminationKeyId": 0,
      "sort": 10
    },
    {
      "content": "{\u0022LineThickness\u0022:\u00220.035mm\u0022,\u0022LineLayer\u0022:\u0022Bottom Layer\u0022,\u0022lineMaterialType\u0022:\u0022Copper\u0022}",
      "contentKey": "impedanceContent_8cf5394a38a8471a8e3dab8f9c29afb3",
      "deleteFlag": false,
      "iaminationType": 1,
      "impedanceIaminationAccessId": null,
      "impedanceIaminationKeyId": 0,
      "sort": 11
    }
  ],
  "impedanceTemplateCode": "20221102070712770",
  "laminationType": 2,
  "compressionThickness": 1.636
}