{
  "templateName": "JLC081011-1080",
  "showName": "JLC081011-1080",
  "stencilLayer": 8,
  "stencilPly": 1,
  "cuprumThickness": 1,
  "insideCuprumThickness": 1,
  "defaultFlag": false,
  "expeditedFlag": false,
  "enableFlag": true,
  "sort": 2,
  "fixedFee": 0,
  "coefficient": 0,
  "iaminationList": [
    {
      "content": "{\u0022LineLayer\u0022:\u0022Layer\u0022,\u0022lineMaterialType\u0022:\u0022Copper\u0022,\u0022LineThickness\u0022:\u00220.035mm\u0022,\u0022coreBoardRemark\u0022:\u0022\u0022}",
      "contentKey": "impedanceContent_2ee17540cf014823bdc5bcf0307d071b",
      "deleteFlag": false,
      "iaminationType": 1,
      "impedanceIaminationAccessId": "2ee17540cf014823bdc5bcf0307d071b",
      "impedanceIaminationKeyId": 1066,
      "sort": 0
    },
    {
      "content": "{\u0022preLayer\u0022:\u0022Prepreg\u0022,\u0022preMaterialType\u0022:\u00221080*1\u0022,\u0022preThickness\u0022:\u00220.069mm\u0022,\u0022coreBoardRemark\u0022:\u0022\u0022}",
      "contentKey": "impedanceContent_b11b63ffb40f4f2794da043ee178d45f",
      "deleteFlag": false,
      "iaminationType": 2,
      "impedanceIaminationAccessId": "b11b63ffb40f4f2794da043ee178d45f",
      "impedanceIaminationKeyId": 1067,
      "sort": 1
    },
    {
      "content": "{\u0022coreBoardLayer1\u0022:\u0022inner Layer\u0022,\u0022coreBoardMaterialType1\u0022:\u0022Copper\u0022,\u0022coreBoardThickness1\u0022:\u00220.03mm\u0022,\u0022coreBoardLayer2\u0022:\u0022Core\u0022,\u0022coreBoardMaterialType2\u0022:\u0022Core\u0022,\u0022coreBoardThickness2\u0022:\u00220.075mm\u0022,\u0022coreBoardLayer3\u0022:\u0022inner Layer\u0022,\u0022coreBoardMaterialType3\u0022:\u0022Copper\u0022,\u0022coreBoardThickness3\u0022:\u00220.03mm\u0022,\u0022coreBoardRemark\u0022:\u00220.075mm (without copper core)\u0022}",
      "contentKey": "impedanceContent_c45ce2eebac3428496e0ddfe3a6d1a36",
      "deleteFlag": false,
      "iaminationType": 3,
      "impedanceIaminationAccessId": "c45ce2eebac3428496e0ddfe3a6d1a36",
      "impedanceIaminationKeyId": 1068,
      "sort": 2
    },
    {
      "content": "{\u0022preLayer\u0022:\u0022Prepreg\u0022,\u0022preMaterialType\u0022:\u00222116*1\u0022,\u0022preThickness\u0022:\u00220.109mm\u0022,\u0022coreBoardRemark\u0022:\u0022\u0022}",
      "contentKey": "impedanceContent_a3edae93390245b69237e3acfe7d2bb5",
      "deleteFlag": false,
      "iaminationType": 2,
      "impedanceIaminationAccessId": "a3edae93390245b69237e3acfe7d2bb5",
      "impedanceIaminationKeyId": 1069,
      "sort": 3
    },
    {
      "content": "{\u0022preLayer\u0022:\u0022Prepreg\u0022,\u0022preMaterialType\u0022:\u00222116*1\u0022,\u0022preThickness\u0022:\u00220.109mm\u0022,\u0022coreBoardRemark\u0022:\u0022\u0022}",
      "contentKey": "impedanceContent_fa2ede9072f141f5b812bc36333099d8",
      "deleteFlag": false,
      "iaminationType": 2,
      "impedanceIaminationAccessId": "fa2ede9072f141f5b812bc36333099d8",
      "impedanceIaminationKeyId": 1070,
      "sort": 4
    },
    {
      "content": "{\u0022coreBoardLayer1\u0022:\u0022inner Layer\u0022,\u0022coreBoardMaterialType1\u0022:\u0022Copper\u0022,\u0022coreBoardThickness1\u0022:\u00220.03mm\u0022,\u0022coreBoardLayer2\u0022:\u0022Core\u0022,\u0022coreBoardMaterialType2\u0022:\u0022Core\u0022,\u0022coreBoardThickness2\u0022:\u00220.075mm\u0022,\u0022coreBoardLayer3\u0022:\u0022inner Layer\u0022,\u0022coreBoardMaterialType3\u0022:\u0022Copper\u0022,\u0022coreBoardThickness3\u0022:\u00220.03mm\u0022,\u0022coreBoardRemark\u0022:\u00220.075mm (without copper core)\u0022}",
      "contentKey": "impedanceContent_fa4ce74bfef246028dc221f3fea490e8",
      "deleteFlag": false,
      "iaminationType": 3,
      "impedanceIaminationAccessId": "fa4ce74bfef246028dc221f3fea490e8",
      "impedanceIaminationKeyId": 1071,
      "sort": 5
    },
    {
      "content": "{\u0022preLayer\u0022:\u0022Prepreg\u0022,\u0022preMaterialType\u0022:\u00222116*1\u0022,\u0022preThickness\u0022:\u00220.109mm\u0022,\u0022coreBoardRemark\u0022:\u0022\u0022}",
      "contentKey": "impedanceContent_bc278396f1f346f7bc20098e9a4445d7",
      "deleteFlag": false,
      "iaminationType": 2,
      "impedanceIaminationAccessId": "bc278396f1f346f7bc20098e9a4445d7",
      "impedanceIaminationKeyId": 1072,
      "sort": 6
    },
    {
      "content": "{\u0022preLayer\u0022:\u0022Prepreg\u0022,\u0022preMaterialType\u0022:\u00222116*1\u0022,\u0022preThickness\u0022:\u00220.109mm\u0022,\u0022coreBoardRemark\u0022:\u0022\u0022}",
      "contentKey": "impedanceContent_84fae1c4765e4bbca18479fc00ed878d",
      "deleteFlag": false,
      "iaminationType": 2,
      "impedanceIaminationAccessId": "84fae1c4765e4bbca18479fc00ed878d",
      "impedanceIaminationKeyId": 1073,
      "sort": 7
    },
    {
      "content": "{\u0022coreBoardLayer1\u0022:\u0022inner Layer\u0022,\u0022coreBoardMaterialType1\u0022:\u0022Copper\u0022,\u0022coreBoardThickness1\u0022:\u00220.03mm\u0022,\u0022coreBoardLayer2\u0022:\u0022Core\u0022,\u0022coreBoardMaterialType2\u0022:\u0022Core\u0022,\u0022coreBoardThickness2\u0022:\u00220.075mm\u0022,\u0022coreBoardLayer3\u0022:\u0022inner Layer\u0022,\u0022coreBoardMaterialType3\u0022:\u0022Copper\u0022,\u0022coreBoardThickness3\u0022:\u00220.03mm\u0022,\u0022coreBoardRemark\u0022:\u00220.075mm (without copper core)\u0022}",
      "contentKey": "impedanceContent_4e3f38ab10444a8893369f3dbc175960",
      "deleteFlag": false,
      "iaminationType": 3,
      "impedanceIaminationAccessId": "4e3f38ab10444a8893369f3dbc175960",
      "impedanceIaminationKeyId": 1074,
      "sort": 8
    },
    {
      "content": "{\u0022preLayer\u0022:\u0022Prepreg\u0022,\u0022preMaterialType\u0022:\u00221080*1\u0022,\u0022preThickness\u0022:\u00220.069mm\u0022,\u0022coreBoardRemark\u0022:\u0022\u0022}",
      "contentKey": "impedanceContent_f970d0dd54f3433dbc0b45cf25817492",
      "deleteFlag": false,
      "iaminationType": 2,
      "impedanceIaminationAccessId": "f970d0dd54f3433dbc0b45cf25817492",
      "impedanceIaminationKeyId": 1075,
      "sort": 9
    },
    {
      "content": "{\u0022LineLayer\u0022:\u0022Layer\u0022,\u0022lineMaterialType\u0022:\u0022Copper\u0022,\u0022LineThickness\u0022:\u00220.035mm\u0022,\u0022coreBoardRemark\u0022:\u0022\u0022}",
      "contentKey": "impedanceContent_709c9363a86444648576273315e51258",
      "deleteFlag": false,
      "iaminationType": 1,
      "impedanceIaminationAccessId": "709c9363a86444648576273315e51258",
      "impedanceIaminationKeyId": 1076,
      "sort": 10
    }
  ],
  "impedanceTemplateCode": "20220327113429",
  "laminationType": 1,
  "compressionThickness": 1.049
}