{
  "templateName": "JLC04202H-7628",
  "showName": "JLC04202H-7628",
  "stencilLayer": 4,
  "stencilPly": 2,
  "cuprumThickness": 2,
  "insideCuprumThickness": 0.5,
  "defaultFlag": false,
  "expeditedFlag": false,
  "enableFlag": true,
  "sort": 2,
  "fixedFee": 0,
  "coefficient": 0,
  "iaminationList": [
    {
      "content": "{\u0022LineThickness\u0022:\u00220.07mm\u0022,\u0022LineLayer\u0022:\u0022Top Layer\u0022,\u0022lineMaterialType\u0022:\u0022Copper\u0022}",
      "contentKey": "impedanceContent_d13a9bf868aa4949baa67f0ed8e38d6c",
      "deleteFlag": false,
      "iaminationType": 1,
      "impedanceIaminationAccessId": null,
      "impedanceIaminationKeyId": 0,
      "sort": 1
    },
    {
      "content": "{\u0022preMaterialType\u0022:\u00227628*1\u0022,\u0022preThickness\u0022:\u00220.21040mm\u0022,\u0022preLayer\u0022:\u0022Prepreg\u0022}",
      "contentKey": "impedanceContent_cd7426411e864d68a9c052dec6c32185",
      "deleteFlag": false,
      "iaminationType": 2,
      "impedanceIaminationAccessId": null,
      "impedanceIaminationKeyId": 0,
      "sort": 2
    },
    {
      "content": "{\u0022coreBoardThickness3\u0022:\u00220.0152mm\u0022,\u0022coreBoardThickness2\u0022:\u00221.465mm\u0022,\u0022coreBoardLayer1\u0022:\u0022Inner Layer L2\u0022,\u0022coreBoardThickness1\u0022:\u00220.0152mm\u0022,\u0022coreBoardRemark\u0022:\u00221.5mm  H/HOZwith copper\u0022,\u0022coreBoardMaterialType1\u0022:\u0022Copper\u0022,\u0022coreBoardMaterialType2\u0022:\u0022Core\u0022,\u0022coreBoardMaterialType3\u0022:\u0022Copper\u0022,\u0022coreBoardLayer2\u0022:\u0022Core\u0022,\u0022coreBoardLayer3\u0022:\u0022Inner Layer L3\u0022}",
      "contentKey": "impedanceContent_1e021981db904087ae7c745d3889e449",
      "deleteFlag": false,
      "iaminationType": 3,
      "impedanceIaminationAccessId": null,
      "impedanceIaminationKeyId": 0,
      "sort": 3
    },
    {
      "content": "{\u0022preMaterialType\u0022:\u00227628*1\u0022,\u0022preThickness\u0022:\u00220.21040mm\u0022,\u0022preLayer\u0022:\u0022Prepreg\u0022}",
      "contentKey": "impedanceContent_ab6f3bf26cde474ebb6c691f54f7251b",
      "deleteFlag": false,
      "iaminationType": 2,
      "impedanceIaminationAccessId": null,
      "impedanceIaminationKeyId": 0,
      "sort": 4
    },
    {
      "content": "{\u0022LineThickness\u0022:\u00220.07mm\u0022,\u0022LineLayer\u0022:\u0022Bottom Layer\u0022,\u0022lineMaterialType\u0022:\u0022Copper\u0022}",
      "contentKey": "impedanceContent_eb4b94d3b7304343872310dfd603a210",
      "deleteFlag": false,
      "iaminationType": 1,
      "impedanceIaminationAccessId": null,
      "impedanceIaminationKeyId": 0,
      "sort": 5
    }
  ],
  "impedanceTemplateCode": "20220617082352",
  "laminationType": 1,
  "compressionThickness": 2.0562
}