{
  "templateName": "JLC041011-2116",
  "showName": "JLC041011-2116",
  "stencilLayer": 4,
  "stencilPly": 1,
  "cuprumThickness": 1,
  "insideCuprumThickness": 1,
  "defaultFlag": false,
  "expeditedFlag": true,
  "enableFlag": true,
  "sort": 6,
  "fixedFee": 330,
  "coefficient": 110,
  "iaminationList": [
    {
      "content": "{\u0022LineLayer\u0022:\u0022Layer\u0022,\u0022lineMaterialType\u0022:\u0022Copper\u0022,\u0022LineThickness\u0022:\u00220.035mm\u0022,\u0022coreBoardRemark\u0022:\u0022\u0022}",
      "contentKey": "impedanceContent_3000ca2750204aa98495acadf5f4b5a3",
      "deleteFlag": false,
      "iaminationType": 1,
      "impedanceIaminationAccessId": "3000ca2750204aa98495acadf5f4b5a3",
      "impedanceIaminationKeyId": 2808,
      "sort": 0
    },
    {
      "content": "{\u0022preLayer\u0022:\u0022Prepreg\u0022,\u0022preMaterialType\u0022:\u00222116*1\u0022,\u0022preThickness\u0022:\u00220.124mm\u0022,\u0022coreBoardRemark\u0022:\u0022\u0022}",
      "contentKey": "impedanceContent_32add81febeb4202b1e82d92d8f61963",
      "deleteFlag": false,
      "iaminationType": 2,
      "impedanceIaminationAccessId": "32add81febeb4202b1e82d92d8f61963",
      "impedanceIaminationKeyId": 2809,
      "sort": 1
    },
    {
      "content": "{\u0022preLayer\u0022:\u0022Prepreg\u0022,\u0022preMaterialType\u0022:\u00227628*1\u0022,\u0022preThickness\u0022:\u00220.203mm\u0022,\u0022coreBoardRemark\u0022:\u0022\u0022}",
      "contentKey": "impedanceContent_33d884a2c5b047dba61da5baa994480e",
      "deleteFlag": false,
      "iaminationType": 2,
      "impedanceIaminationAccessId": "33d884a2c5b047dba61da5baa994480e",
      "impedanceIaminationKeyId": 2810,
      "sort": 2
    },
    {
      "content": "{\u0022coreBoardLayer1\u0022:\u0022inner Layer\u0022,\u0022coreBoardMaterialType1\u0022:\u0022Copper\u0022,\u0022coreBoardThickness1\u0022:\u00220.03mm\u0022,\u0022coreBoardLayer2\u0022:\u0022Core\u0022,\u0022coreBoardMaterialType2\u0022:\u0022Core\u0022,\u0022coreBoardThickness2\u0022:\u00220.25mm\u0022,\u0022coreBoardLayer3\u0022:\u0022inner Layer\u0022,\u0022coreBoardMaterialType3\u0022:\u0022Copper\u0022,\u0022coreBoardThickness3\u0022:\u00220.03mm\u0022,\u0022coreBoardRemark\u0022:\u00220.25mm (without copper core)\u0022}",
      "contentKey": "impedanceContent_a3e344a9454c42589c47d5fcddef34ee",
      "deleteFlag": false,
      "iaminationType": 3,
      "impedanceIaminationAccessId": "a3e344a9454c42589c47d5fcddef34ee",
      "impedanceIaminationKeyId": 2811,
      "sort": 3
    },
    {
      "content": "{\u0022preLayer\u0022:\u0022Prepreg\u0022,\u0022preMaterialType\u0022:\u00227628*1\u0022,\u0022preThickness\u0022:\u00220.203mm\u0022,\u0022coreBoardRemark\u0022:\u0022\u0022}",
      "contentKey": "impedanceContent_8ffc849951f446f0b2f7ca1129afe897",
      "deleteFlag": false,
      "iaminationType": 2,
      "impedanceIaminationAccessId": "8ffc849951f446f0b2f7ca1129afe897",
      "impedanceIaminationKeyId": 2812,
      "sort": 4
    },
    {
      "content": "{\u0022preLayer\u0022:\u0022Prepreg\u0022,\u0022preMaterialType\u0022:\u00222116*1\u0022,\u0022preThickness\u0022:\u00220.124mm\u0022,\u0022coreBoardRemark\u0022:\u0022\u0022}",
      "contentKey": "impedanceContent_d4409ce23a4f40a59b9d9e652e3608f4",
      "deleteFlag": false,
      "iaminationType": 2,
      "impedanceIaminationAccessId": "d4409ce23a4f40a59b9d9e652e3608f4",
      "impedanceIaminationKeyId": 2813,
      "sort": 5
    },
    {
      "content": "{\u0022LineLayer\u0022:\u0022Layer\u0022,\u0022lineMaterialType\u0022:\u0022Copper\u0022,\u0022LineThickness\u0022:\u00220.035mm\u0022,\u0022coreBoardRemark\u0022:\u0022\u0022}",
      "contentKey": "impedanceContent_b6abed8bc3244582b9167a2c0e0daf38",
      "deleteFlag": false,
      "iaminationType": 1,
      "impedanceIaminationAccessId": "b6abed8bc3244582b9167a2c0e0daf38",
      "impedanceIaminationKeyId": 2814,
      "sort": 6
    }
  ],
  "impedanceTemplateCode": "20220928022501692",
  "laminationType": 2,
  "compressionThickness": 1.034
}