{
  "templateName": "JLC263511-2116",
  "showName": "JLC263511-2116",
  "stencilLayer": 26,
  "stencilPly": 3.5,
  "cuprumThickness": 1,
  "insideCuprumThickness": 1,
  "defaultFlag": true,
  "expeditedFlag": false,
  "enableFlag": true,
  "sort": 6,
  "fixedFee": 0,
  "coefficient": 0,
  "iaminationList": [
    {
      "content": "{\u0022LineLayer\u0022:\u0022Layer\u0022,\u0022lineMaterialType\u0022:\u0022Copper\u0022,\u0022LineThickness\u0022:\u00220.035mm\u0022,\u0022coreBoardRemark\u0022:\u0022\u0022}",
      "contentKey": "impedanceContent_db54332bd903409d915f1978a8c952d6",
      "deleteFlag": false,
      "iaminationType": 1,
      "impedanceIaminationAccessId": "db54332bd903409d915f1978a8c952d6",
      "impedanceIaminationKeyId": 7723,
      "sort": 0
    },
    {
      "content": "{\u0022preLayer\u0022:\u0022Prepreg\u0022,\u0022preMaterialType\u0022:\u00222116*1\u0022,\u0022preThickness\u0022:\u00220.112mm\u0022,\u0022coreBoardRemark\u0022:\u0022\u0022}",
      "contentKey": "impedanceContent_f038b2b197a548c682eb6f76162ee5ea",
      "deleteFlag": false,
      "iaminationType": 2,
      "impedanceIaminationAccessId": "f038b2b197a548c682eb6f76162ee5ea",
      "impedanceIaminationKeyId": 7724,
      "sort": 1
    },
    {
      "content": "{\u0022coreBoardLayer1\u0022:\u0022inner Layer\u0022,\u0022coreBoardMaterialType1\u0022:\u0022Copper\u0022,\u0022coreBoardThickness1\u0022:\u00220.03mm\u0022,\u0022coreBoardLayer2\u0022:\u0022Core\u0022,\u0022coreBoardMaterialType2\u0022:\u0022Core\u0022,\u0022coreBoardThickness2\u0022:\u00220.075mm\u0022,\u0022coreBoardLayer3\u0022:\u0022inner Layer\u0022,\u0022coreBoardMaterialType3\u0022:\u0022Copper\u0022,\u0022coreBoardThickness3\u0022:\u00220.03mm\u0022,\u0022coreBoardRemark\u0022:\u00220.075m(without copper core)\u0022}",
      "contentKey": "impedanceContent_29e45bf03c6d4447aacc605e3e176b2e",
      "deleteFlag": false,
      "iaminationType": 3,
      "impedanceIaminationAccessId": "29e45bf03c6d4447aacc605e3e176b2e",
      "impedanceIaminationKeyId": 7725,
      "sort": 2
    },
    {
      "content": "{\u0022preLayer\u0022:\u0022Prepreg\u0022,\u0022preMaterialType\u0022:\u00221080*1\u0022,\u0022preThickness\u0022:\u00220.071mm\u0022,\u0022coreBoardRemark\u0022:\u0022\u0022}",
      "contentKey": "impedanceContent_23c3ef01049e499faa86ad89a381fd4c",
      "deleteFlag": false,
      "iaminationType": 2,
      "impedanceIaminationAccessId": "23c3ef01049e499faa86ad89a381fd4c",
      "impedanceIaminationKeyId": 7726,
      "sort": 3
    },
    {
      "content": "{\u0022preLayer\u0022:\u0022Prepreg\u0022,\u0022preMaterialType\u0022:\u00221080*1\u0022,\u0022preThickness\u0022:\u00220.071mm\u0022,\u0022coreBoardRemark\u0022:\u0022\u0022}",
      "contentKey": "impedanceContent_c6d79e7f696f4b099414ec0f61332088",
      "deleteFlag": false,
      "iaminationType": 2,
      "impedanceIaminationAccessId": "c6d79e7f696f4b099414ec0f61332088",
      "impedanceIaminationKeyId": 7727,
      "sort": 4
    },
    {
      "content": "{\u0022coreBoardLayer1\u0022:\u0022inner Layer\u0022,\u0022coreBoardMaterialType1\u0022:\u0022Copper\u0022,\u0022coreBoardThickness1\u0022:\u00220.03mm\u0022,\u0022coreBoardLayer2\u0022:\u0022Core\u0022,\u0022coreBoardMaterialType2\u0022:\u0022Core\u0022,\u0022coreBoardThickness2\u0022:\u00220.075mm\u0022,\u0022coreBoardLayer3\u0022:\u0022inner Layer\u0022,\u0022coreBoardMaterialType3\u0022:\u0022Copper\u0022,\u0022coreBoardThickness3\u0022:\u00220.03mm\u0022,\u0022coreBoardRemark\u0022:\u00220.075m(without copper core)\u0022}",
      "contentKey": "impedanceContent_d106ff999d1b421f8c345cbdb6872dde",
      "deleteFlag": false,
      "iaminationType": 3,
      "impedanceIaminationAccessId": "d106ff999d1b421f8c345cbdb6872dde",
      "impedanceIaminationKeyId": 7728,
      "sort": 5
    },
    {
      "content": "{\u0022preLayer\u0022:\u0022Prepreg\u0022,\u0022preMaterialType\u0022:\u00221080*1\u0022,\u0022preThickness\u0022:\u00220.071mm\u0022,\u0022coreBoardRemark\u0022:\u0022\u0022}",
      "contentKey": "impedanceContent_1f34cd6e153a4194b843aef8b29444b4",
      "deleteFlag": false,
      "iaminationType": 2,
      "impedanceIaminationAccessId": "1f34cd6e153a4194b843aef8b29444b4",
      "impedanceIaminationKeyId": 7729,
      "sort": 6
    },
    {
      "content": "{\u0022preLayer\u0022:\u0022Prepreg\u0022,\u0022preMaterialType\u0022:\u00221080*1\u0022,\u0022preThickness\u0022:\u00220.071mm\u0022,\u0022coreBoardRemark\u0022:\u0022\u0022}",
      "contentKey": "impedanceContent_3047460dfba34b23abc9f0432bfc76d6",
      "deleteFlag": false,
      "iaminationType": 2,
      "impedanceIaminationAccessId": "3047460dfba34b23abc9f0432bfc76d6",
      "impedanceIaminationKeyId": 7730,
      "sort": 7
    },
    {
      "content": "{\u0022coreBoardLayer1\u0022:\u0022inner Layer\u0022,\u0022coreBoardMaterialType1\u0022:\u0022Copper\u0022,\u0022coreBoardThickness1\u0022:\u00220.03mm\u0022,\u0022coreBoardLayer2\u0022:\u0022Core\u0022,\u0022coreBoardMaterialType2\u0022:\u0022Core\u0022,\u0022coreBoardThickness2\u0022:\u00220.075mm\u0022,\u0022coreBoardLayer3\u0022:\u0022inner Layer\u0022,\u0022coreBoardMaterialType3\u0022:\u0022Copper\u0022,\u0022coreBoardThickness3\u0022:\u00220.03mm\u0022,\u0022coreBoardRemark\u0022:\u00220.075m(without copper core)\u0022}",
      "contentKey": "impedanceContent_5563e3dee511465d8662ef7ead0bfbe3",
      "deleteFlag": false,
      "iaminationType": 3,
      "impedanceIaminationAccessId": "5563e3dee511465d8662ef7ead0bfbe3",
      "impedanceIaminationKeyId": 7731,
      "sort": 8
    },
    {
      "content": "{\u0022preLayer\u0022:\u0022Prepreg\u0022,\u0022preMaterialType\u0022:\u00221080*1\u0022,\u0022preThickness\u0022:\u00220.071mm\u0022,\u0022coreBoardRemark\u0022:\u0022\u0022}",
      "contentKey": "impedanceContent_6eac7ea681814426b5fa6be12257d5a5",
      "deleteFlag": false,
      "iaminationType": 2,
      "impedanceIaminationAccessId": "6eac7ea681814426b5fa6be12257d5a5",
      "impedanceIaminationKeyId": 7732,
      "sort": 9
    },
    {
      "content": "{\u0022preLayer\u0022:\u0022Prepreg\u0022,\u0022preMaterialType\u0022:\u00221080*1\u0022,\u0022preThickness\u0022:\u00220.071mm\u0022,\u0022coreBoardRemark\u0022:\u0022\u0022}",
      "contentKey": "impedanceContent_9ad3d5cdea8848d0b5a4714782a2ea39",
      "deleteFlag": false,
      "iaminationType": 2,
      "impedanceIaminationAccessId": "9ad3d5cdea8848d0b5a4714782a2ea39",
      "impedanceIaminationKeyId": 7733,
      "sort": 10
    },
    {
      "content": "{\u0022coreBoardLayer1\u0022:\u0022inner Layer\u0022,\u0022coreBoardMaterialType1\u0022:\u0022Copper\u0022,\u0022coreBoardThickness1\u0022:\u00220.03mm\u0022,\u0022coreBoardLayer2\u0022:\u0022Core\u0022,\u0022coreBoardMaterialType2\u0022:\u0022Core\u0022,\u0022coreBoardThickness2\u0022:\u00220.075mm\u0022,\u0022coreBoardLayer3\u0022:\u0022inner Layer\u0022,\u0022coreBoardMaterialType3\u0022:\u0022Copper\u0022,\u0022coreBoardThickness3\u0022:\u00220.03mm\u0022,\u0022coreBoardRemark\u0022:\u00220.075m(without copper core)\u0022}",
      "contentKey": "impedanceContent_c0137b36f94648e18d35ae16471870cc",
      "deleteFlag": false,
      "iaminationType": 3,
      "impedanceIaminationAccessId": "c0137b36f94648e18d35ae16471870cc",
      "impedanceIaminationKeyId": 7734,
      "sort": 11
    },
    {
      "content": "{\u0022preLayer\u0022:\u0022Prepreg\u0022,\u0022preMaterialType\u0022:\u00221080*1\u0022,\u0022preThickness\u0022:\u00220.071mm\u0022,\u0022coreBoardRemark\u0022:\u0022\u0022}",
      "contentKey": "impedanceContent_35aeb925b283482883ed989811de7441",
      "deleteFlag": false,
      "iaminationType": 2,
      "impedanceIaminationAccessId": "35aeb925b283482883ed989811de7441",
      "impedanceIaminationKeyId": 7735,
      "sort": 12
    },
    {
      "content": "{\u0022preLayer\u0022:\u0022Prepreg\u0022,\u0022preMaterialType\u0022:\u00221080*1\u0022,\u0022preThickness\u0022:\u00220.071mm\u0022,\u0022coreBoardRemark\u0022:\u0022\u0022}",
      "contentKey": "impedanceContent_b066ed025c6847799e8a5d1dd00b8bf0",
      "deleteFlag": false,
      "iaminationType": 2,
      "impedanceIaminationAccessId": "b066ed025c6847799e8a5d1dd00b8bf0",
      "impedanceIaminationKeyId": 7736,
      "sort": 13
    },
    {
      "content": "{\u0022coreBoardLayer1\u0022:\u0022inner Layer\u0022,\u0022coreBoardMaterialType1\u0022:\u0022Copper\u0022,\u0022coreBoardThickness1\u0022:\u00220.03mm\u0022,\u0022coreBoardLayer2\u0022:\u0022Core\u0022,\u0022coreBoardMaterialType2\u0022:\u0022Core\u0022,\u0022coreBoardThickness2\u0022:\u00220.075mm\u0022,\u0022coreBoardLayer3\u0022:\u0022inner Layer\u0022,\u0022coreBoardMaterialType3\u0022:\u0022Copper\u0022,\u0022coreBoardThickness3\u0022:\u00220.03mm\u0022,\u0022coreBoardRemark\u0022:\u00220.075m(without copper core)\u0022}",
      "contentKey": "impedanceContent_bc41670d705b477db6d0e661243ddbb4",
      "deleteFlag": false,
      "iaminationType": 3,
      "impedanceIaminationAccessId": "bc41670d705b477db6d0e661243ddbb4",
      "impedanceIaminationKeyId": 7737,
      "sort": 14
    },
    {
      "content": "{\u0022preLayer\u0022:\u0022Prepreg\u0022,\u0022preMaterialType\u0022:\u00221080*1\u0022,\u0022preThickness\u0022:\u00220.071mm\u0022,\u0022coreBoardRemark\u0022:\u0022\u0022}",
      "contentKey": "impedanceContent_2f173e053a5f4b0cb4cf3c2ff687eb34",
      "deleteFlag": false,
      "iaminationType": 2,
      "impedanceIaminationAccessId": "2f173e053a5f4b0cb4cf3c2ff687eb34",
      "impedanceIaminationKeyId": 7738,
      "sort": 15
    },
    {
      "content": "{\u0022preLayer\u0022:\u0022Prepreg\u0022,\u0022preMaterialType\u0022:\u00221080*1\u0022,\u0022preThickness\u0022:\u00220.071mm\u0022,\u0022coreBoardRemark\u0022:\u0022\u0022}",
      "contentKey": "impedanceContent_4a42c35c32d34c79a6b2cc4f6ce74da3",
      "deleteFlag": false,
      "iaminationType": 2,
      "impedanceIaminationAccessId": "4a42c35c32d34c79a6b2cc4f6ce74da3",
      "impedanceIaminationKeyId": 7739,
      "sort": 16
    },
    {
      "content": "{\u0022coreBoardLayer1\u0022:\u0022inner Layer\u0022,\u0022coreBoardMaterialType1\u0022:\u0022Copper\u0022,\u0022coreBoardThickness1\u0022:\u00220.03mm\u0022,\u0022coreBoardLayer2\u0022:\u0022Core\u0022,\u0022coreBoardMaterialType2\u0022:\u0022Core\u0022,\u0022coreBoardThickness2\u0022:\u00220.075mm\u0022,\u0022coreBoardLayer3\u0022:\u0022inner Layer\u0022,\u0022coreBoardMaterialType3\u0022:\u0022Copper\u0022,\u0022coreBoardThickness3\u0022:\u00220.03mm\u0022,\u0022coreBoardRemark\u0022:\u00220.075m(without copper core)\u0022}",
      "contentKey": "impedanceContent_c171f9da44284feaa02576287003064b",
      "deleteFlag": false,
      "iaminationType": 3,
      "impedanceIaminationAccessId": "c171f9da44284feaa02576287003064b",
      "impedanceIaminationKeyId": 7740,
      "sort": 17
    },
    {
      "content": "{\u0022preLayer\u0022:\u0022Prepreg\u0022,\u0022preMaterialType\u0022:\u00221080*1\u0022,\u0022preThickness\u0022:\u00220.071mm\u0022,\u0022coreBoardRemark\u0022:\u0022\u0022}",
      "contentKey": "impedanceContent_1e847c17a90f416da6e78ba86955c42b",
      "deleteFlag": false,
      "iaminationType": 2,
      "impedanceIaminationAccessId": "1e847c17a90f416da6e78ba86955c42b",
      "impedanceIaminationKeyId": 7741,
      "sort": 18
    },
    {
      "content": "{\u0022preLayer\u0022:\u0022Prepreg\u0022,\u0022preMaterialType\u0022:\u00221080*1\u0022,\u0022preThickness\u0022:\u00220.071mm\u0022,\u0022coreBoardRemark\u0022:\u0022\u0022}",
      "contentKey": "impedanceContent_77f5cb72673e441384021b55eca20b1c",
      "deleteFlag": false,
      "iaminationType": 2,
      "impedanceIaminationAccessId": "77f5cb72673e441384021b55eca20b1c",
      "impedanceIaminationKeyId": 7742,
      "sort": 19
    },
    {
      "content": "{\u0022coreBoardLayer1\u0022:\u0022inner Layer\u0022,\u0022coreBoardMaterialType1\u0022:\u0022Copper\u0022,\u0022coreBoardThickness1\u0022:\u00220.03mm\u0022,\u0022coreBoardLayer2\u0022:\u0022Core\u0022,\u0022coreBoardMaterialType2\u0022:\u0022Core\u0022,\u0022coreBoardThickness2\u0022:\u00220.075mm\u0022,\u0022coreBoardLayer3\u0022:\u0022inner Layer\u0022,\u0022coreBoardMaterialType3\u0022:\u0022Copper\u0022,\u0022coreBoardThickness3\u0022:\u00220.03mm\u0022,\u0022coreBoardRemark\u0022:\u00220.075m(without copper core)\u0022}",
      "contentKey": "impedanceContent_c715a6b8dd114d1b8d46f9425e8f9978",
      "deleteFlag": false,
      "iaminationType": 3,
      "impedanceIaminationAccessId": "c715a6b8dd114d1b8d46f9425e8f9978",
      "impedanceIaminationKeyId": 7743,
      "sort": 20
    },
    {
      "content": "{\u0022preLayer\u0022:\u0022Prepreg\u0022,\u0022preMaterialType\u0022:\u00221080*1\u0022,\u0022preThickness\u0022:\u00220.071mm\u0022,\u0022coreBoardRemark\u0022:\u0022\u0022}",
      "contentKey": "impedanceContent_931cc372effc42f2873a108df590bb71",
      "deleteFlag": false,
      "iaminationType": 2,
      "impedanceIaminationAccessId": "931cc372effc42f2873a108df590bb71",
      "impedanceIaminationKeyId": 7744,
      "sort": 21
    },
    {
      "content": "{\u0022preLayer\u0022:\u0022Prepreg\u0022,\u0022preMaterialType\u0022:\u00221080*1\u0022,\u0022preThickness\u0022:\u00220.071mm\u0022,\u0022coreBoardRemark\u0022:\u0022\u0022}",
      "contentKey": "impedanceContent_c995a1242f7b4296a71b4066a267460f",
      "deleteFlag": false,
      "iaminationType": 2,
      "impedanceIaminationAccessId": "c995a1242f7b4296a71b4066a267460f",
      "impedanceIaminationKeyId": 7745,
      "sort": 22
    },
    {
      "content": "{\u0022coreBoardLayer1\u0022:\u0022inner Layer\u0022,\u0022coreBoardMaterialType1\u0022:\u0022Copper\u0022,\u0022coreBoardThickness1\u0022:\u00220.03mm\u0022,\u0022coreBoardLayer2\u0022:\u0022Core\u0022,\u0022coreBoardMaterialType2\u0022:\u0022Core\u0022,\u0022coreBoardThickness2\u0022:\u00220.075mm\u0022,\u0022coreBoardLayer3\u0022:\u0022inner Layer\u0022,\u0022coreBoardMaterialType3\u0022:\u0022Copper\u0022,\u0022coreBoardThickness3\u0022:\u00220.03mm\u0022,\u0022coreBoardRemark\u0022:\u00220.075m(without copper core)\u0022}",
      "contentKey": "impedanceContent_af37098c5f674e6e81e3fd8e08a96c15",
      "deleteFlag": false,
      "iaminationType": 3,
      "impedanceIaminationAccessId": "af37098c5f674e6e81e3fd8e08a96c15",
      "impedanceIaminationKeyId": 7746,
      "sort": 23
    },
    {
      "content": "{\u0022preLayer\u0022:\u0022Prepreg\u0022,\u0022preMaterialType\u0022:\u00221080*1\u0022,\u0022preThickness\u0022:\u00220.071mm\u0022,\u0022coreBoardRemark\u0022:\u0022\u0022}",
      "contentKey": "impedanceContent_22ae266fbe2e4260a9b250bb86986d83",
      "deleteFlag": false,
      "iaminationType": 2,
      "impedanceIaminationAccessId": "22ae266fbe2e4260a9b250bb86986d83",
      "impedanceIaminationKeyId": 7747,
      "sort": 24
    },
    {
      "content": "{\u0022preLayer\u0022:\u0022Prepreg\u0022,\u0022preMaterialType\u0022:\u00221080*1\u0022,\u0022preThickness\u0022:\u00220.071mm\u0022,\u0022coreBoardRemark\u0022:\u0022\u0022}",
      "contentKey": "impedanceContent_780a32cb21fe483c96c958d8fb68615d",
      "deleteFlag": false,
      "iaminationType": 2,
      "impedanceIaminationAccessId": "780a32cb21fe483c96c958d8fb68615d",
      "impedanceIaminationKeyId": 7748,
      "sort": 25
    },
    {
      "content": "{\u0022coreBoardLayer1\u0022:\u0022inner Layer\u0022,\u0022coreBoardMaterialType1\u0022:\u0022Copper\u0022,\u0022coreBoardThickness1\u0022:\u00220.03mm\u0022,\u0022coreBoardLayer2\u0022:\u0022Core\u0022,\u0022coreBoardMaterialType2\u0022:\u0022Core\u0022,\u0022coreBoardThickness2\u0022:\u00220.075mm\u0022,\u0022coreBoardLayer3\u0022:\u0022inner Layer\u0022,\u0022coreBoardMaterialType3\u0022:\u0022Copper\u0022,\u0022coreBoardThickness3\u0022:\u00220.03mm\u0022,\u0022coreBoardRemark\u0022:\u00220.075m(without copper core)\u0022}",
      "contentKey": "impedanceContent_cb3d70ae6f5941cdb0cbc0e251ebcf70",
      "deleteFlag": false,
      "iaminationType": 3,
      "impedanceIaminationAccessId": "cb3d70ae6f5941cdb0cbc0e251ebcf70",
      "impedanceIaminationKeyId": 7749,
      "sort": 26
    },
    {
      "content": "{\u0022preLayer\u0022:\u0022Prepreg\u0022,\u0022preMaterialType\u0022:\u00221080*1\u0022,\u0022preThickness\u0022:\u00220.071mm\u0022,\u0022coreBoardRemark\u0022:\u0022\u0022}",
      "contentKey": "impedanceContent_ec349b132bdc4ded904ba52c2ec92ff1",
      "deleteFlag": false,
      "iaminationType": 2,
      "impedanceIaminationAccessId": "ec349b132bdc4ded904ba52c2ec92ff1",
      "impedanceIaminationKeyId": 7750,
      "sort": 27
    },
    {
      "content": "{\u0022preLayer\u0022:\u0022Prepreg\u0022,\u0022preMaterialType\u0022:\u00221080*1\u0022,\u0022preThickness\u0022:\u00220.071mm\u0022,\u0022coreBoardRemark\u0022:\u0022\u0022}",
      "contentKey": "impedanceContent_b30bc08f0270401195c9d19978a078cc",
      "deleteFlag": false,
      "iaminationType": 2,
      "impedanceIaminationAccessId": "b30bc08f0270401195c9d19978a078cc",
      "impedanceIaminationKeyId": 7751,
      "sort": 28
    },
    {
      "content": "{\u0022coreBoardLayer1\u0022:\u0022inner Layer\u0022,\u0022coreBoardMaterialType1\u0022:\u0022Copper\u0022,\u0022coreBoardThickness1\u0022:\u00220.03mm\u0022,\u0022coreBoardLayer2\u0022:\u0022Core\u0022,\u0022coreBoardMaterialType2\u0022:\u0022Core\u0022,\u0022coreBoardThickness2\u0022:\u00220.075mm\u0022,\u0022coreBoardLayer3\u0022:\u0022inner Layer\u0022,\u0022coreBoardMaterialType3\u0022:\u0022Copper\u0022,\u0022coreBoardThickness3\u0022:\u00220.03mm\u0022,\u0022coreBoardRemark\u0022:\u00220.075m(without copper core)\u0022}",
      "contentKey": "impedanceContent_ca3b75832f25436bae6184a1d6d93724",
      "deleteFlag": false,
      "iaminationType": 3,
      "impedanceIaminationAccessId": "ca3b75832f25436bae6184a1d6d93724",
      "impedanceIaminationKeyId": 7752,
      "sort": 29
    },
    {
      "content": "{\u0022preLayer\u0022:\u0022Prepreg\u0022,\u0022preMaterialType\u0022:\u00221080*1\u0022,\u0022preThickness\u0022:\u00220.071mm\u0022,\u0022coreBoardRemark\u0022:\u0022\u0022}",
      "contentKey": "impedanceContent_ca2a9b1e98e74f5eb4c89043ae700b08",
      "deleteFlag": false,
      "iaminationType": 2,
      "impedanceIaminationAccessId": "ca2a9b1e98e74f5eb4c89043ae700b08",
      "impedanceIaminationKeyId": 7753,
      "sort": 30
    },
    {
      "content": "{\u0022preLayer\u0022:\u0022Prepreg\u0022,\u0022preMaterialType\u0022:\u00221080*1\u0022,\u0022preThickness\u0022:\u00220.071mm\u0022,\u0022coreBoardRemark\u0022:\u0022\u0022}",
      "contentKey": "impedanceContent_0ea6a601020f455c96a04404d04c1a30",
      "deleteFlag": false,
      "iaminationType": 2,
      "impedanceIaminationAccessId": "0ea6a601020f455c96a04404d04c1a30",
      "impedanceIaminationKeyId": 7754,
      "sort": 31
    },
    {
      "content": "{\u0022coreBoardLayer1\u0022:\u0022inner Layer\u0022,\u0022coreBoardMaterialType1\u0022:\u0022Copper\u0022,\u0022coreBoardThickness1\u0022:\u00220.03mm\u0022,\u0022coreBoardLayer2\u0022:\u0022Core\u0022,\u0022coreBoardMaterialType2\u0022:\u0022Core\u0022,\u0022coreBoardThickness2\u0022:\u00220.075mm\u0022,\u0022coreBoardLayer3\u0022:\u0022inner Layer\u0022,\u0022coreBoardMaterialType3\u0022:\u0022Copper\u0022,\u0022coreBoardThickness3\u0022:\u00220.03mm\u0022,\u0022coreBoardRemark\u0022:\u00220.075m(without copper core)\u0022}",
      "contentKey": "impedanceContent_cdb6394f495c478c960a5c38a4075ad7",
      "deleteFlag": false,
      "iaminationType": 3,
      "impedanceIaminationAccessId": "cdb6394f495c478c960a5c38a4075ad7",
      "impedanceIaminationKeyId": 7755,
      "sort": 32
    },
    {
      "content": "{\u0022preLayer\u0022:\u0022Prepreg\u0022,\u0022preMaterialType\u0022:\u00221080*1\u0022,\u0022preThickness\u0022:\u00220.071mm\u0022,\u0022coreBoardRemark\u0022:\u0022\u0022}",
      "contentKey": "impedanceContent_1eff10645e4541f4b068d72de22582b5",
      "deleteFlag": false,
      "iaminationType": 2,
      "impedanceIaminationAccessId": "1eff10645e4541f4b068d72de22582b5",
      "impedanceIaminationKeyId": 7756,
      "sort": 33
    },
    {
      "content": "{\u0022preLayer\u0022:\u0022Prepreg\u0022,\u0022preMaterialType\u0022:\u00221080*1\u0022,\u0022preThickness\u0022:\u00220.071mm\u0022,\u0022coreBoardRemark\u0022:\u0022\u0022}",
      "contentKey": "impedanceContent_e703f994d8b6487bbb62493656dac37a",
      "deleteFlag": false,
      "iaminationType": 2,
      "impedanceIaminationAccessId": "e703f994d8b6487bbb62493656dac37a",
      "impedanceIaminationKeyId": 7757,
      "sort": 34
    },
    {
      "content": "{\u0022coreBoardLayer1\u0022:\u0022inner Layer\u0022,\u0022coreBoardMaterialType1\u0022:\u0022Copper\u0022,\u0022coreBoardThickness1\u0022:\u00220.03mm\u0022,\u0022coreBoardLayer2\u0022:\u0022Core\u0022,\u0022coreBoardMaterialType2\u0022:\u0022Core\u0022,\u0022coreBoardThickness2\u0022:\u00220.075mm\u0022,\u0022coreBoardLayer3\u0022:\u0022inner Layer\u0022,\u0022coreBoardMaterialType3\u0022:\u0022Copper\u0022,\u0022coreBoardThickness3\u0022:\u00220.03mm\u0022,\u0022coreBoardRemark\u0022:\u00220.075m(without copper core)\u0022}",
      "contentKey": "impedanceContent_15266f6c9f4948ea971c68a3e5e1a5a5",
      "deleteFlag": false,
      "iaminationType": 3,
      "impedanceIaminationAccessId": "15266f6c9f4948ea971c68a3e5e1a5a5",
      "impedanceIaminationKeyId": 7758,
      "sort": 35
    },
    {
      "content": "{\u0022preLayer\u0022:\u0022Prepreg\u0022,\u0022preMaterialType\u0022:\u00222116*1\u0022,\u0022preThickness\u0022:\u00220.112mm\u0022,\u0022coreBoardRemark\u0022:\u0022\u0022}",
      "contentKey": "impedanceContent_33c4dcafb8a14bf6bb63704bb41bdd8c",
      "deleteFlag": false,
      "iaminationType": 2,
      "impedanceIaminationAccessId": "33c4dcafb8a14bf6bb63704bb41bdd8c",
      "impedanceIaminationKeyId": 7759,
      "sort": 36
    },
    {
      "content": "{\u0022LineLayer\u0022:\u0022Layer\u0022,\u0022lineMaterialType\u0022:\u0022Copper\u0022,\u0022LineThickness\u0022:\u00220.035mm\u0022,\u0022coreBoardRemark\u0022:\u0022\u0022}",
      "contentKey": "impedanceContent_30acffed32374cfcaaae1b0e7097aba9",
      "deleteFlag": false,
      "iaminationType": 1,
      "impedanceIaminationAccessId": "30acffed32374cfcaaae1b0e7097aba9",
      "impedanceIaminationKeyId": 7760,
      "sort": 37
    }
  ],
  "impedanceTemplateCode": "202308030151301353",
  "laminationType": 1,
  "compressionThickness": 3.476
}