{
  "templateName": "JLC101611-1080C",
  "showName": "JLC101611-1080C",
  "stencilLayer": 10,
  "stencilPly": 1.6,
  "cuprumThickness": 1,
  "insideCuprumThickness": 1,
  "defaultFlag": false,
  "expeditedFlag": false,
  "enableFlag": true,
  "sort": 10,
  "fixedFee": 0,
  "coefficient": 0,
  "iaminationList": [
    {
      "content": "{\u0022LineLayer\u0022:\u0022Layer\u0022,\u0022lineMaterialType\u0022:\u0022Copper\u0022,\u0022LineThickness\u0022:\u00220.035mm\u0022,\u0022coreBoardRemark\u0022:\u0022\u0022}",
      "contentKey": "impedanceContent_f7eee2df2ab34f27975896343ed9a790",
      "deleteFlag": false,
      "iaminationType": 1,
      "impedanceIaminationAccessId": "f7eee2df2ab34f27975896343ed9a790",
      "impedanceIaminationKeyId": 30151,
      "sort": 0
    },
    {
      "content": "{\u0022preLayer\u0022:\u0022Prepreg\u0022,\u0022preMaterialType\u0022:\u00221080\u0022,\u0022preThickness\u0022:\u00220.0710mm\u0022,\u0022coreBoardRemark\u0022:\u0022\u0022}",
      "contentKey": "impedanceContent_9e1733eb679448969545edf5808fe29a",
      "deleteFlag": false,
      "iaminationType": 2,
      "impedanceIaminationAccessId": "9e1733eb679448969545edf5808fe29a",
      "impedanceIaminationKeyId": 30152,
      "sort": 1
    },
    {
      "content": "{\u0022coreBoardLayer1\u0022:\u0022inner Layer\u0022,\u0022coreBoardMaterialType1\u0022:\u0022Copper\u0022,\u0022coreBoardThickness1\u0022:\u00220.0300mm\u0022,\u0022coreBoardLayer2\u0022:\u0022Core\u0022,\u0022coreBoardMaterialType2\u0022:\u0022Core\u0022,\u0022coreBoardThickness2\u0022:\u00220.0750mm\u0022,\u0022coreBoardLayer3\u0022:\u0022inner Layer\u0022,\u0022coreBoardMaterialType3\u0022:\u0022Copper\u0022,\u0022coreBoardThickness3\u0022:\u00220.0300mm\u0022,\u0022coreBoardRemark\u0022:\u00220.075mm(without copper)\u0022}",
      "contentKey": "impedanceContent_e1b6d927f3eb4ef991744f168708a820",
      "deleteFlag": false,
      "iaminationType": 3,
      "impedanceIaminationAccessId": "e1b6d927f3eb4ef991744f168708a820",
      "impedanceIaminationKeyId": 30153,
      "sort": 2
    },
    {
      "content": "{\u0022preLayer\u0022:\u0022Prepreg\u0022,\u0022preMaterialType\u0022:\u00222116\u0022,\u0022preThickness\u0022:\u00220.1120mm\u0022,\u0022coreBoardRemark\u0022:\u0022\u0022}",
      "contentKey": "impedanceContent_af1847cd4d824a8b88b74b4f8d1cf02c",
      "deleteFlag": false,
      "iaminationType": 2,
      "impedanceIaminationAccessId": "af1847cd4d824a8b88b74b4f8d1cf02c",
      "impedanceIaminationKeyId": 30154,
      "sort": 3
    },
    {
      "content": "{\u0022preLayer\u0022:\u0022Prepreg\u0022,\u0022preMaterialType\u0022:\u00222116\u0022,\u0022preThickness\u0022:\u00220.1120mm\u0022,\u0022coreBoardRemark\u0022:\u0022\u0022}",
      "contentKey": "impedanceContent_e51cc5e6ae85445a9800f936c6f55ada",
      "deleteFlag": false,
      "iaminationType": 2,
      "impedanceIaminationAccessId": "e51cc5e6ae85445a9800f936c6f55ada",
      "impedanceIaminationKeyId": 30155,
      "sort": 4
    },
    {
      "content": "{\u0022coreBoardLayer1\u0022:\u0022inner Layer\u0022,\u0022coreBoardMaterialType1\u0022:\u0022Copper\u0022,\u0022coreBoardThickness1\u0022:\u00220.0300mm\u0022,\u0022coreBoardLayer2\u0022:\u0022Core\u0022,\u0022coreBoardMaterialType2\u0022:\u0022Core\u0022,\u0022coreBoardThickness2\u0022:\u00220.0750mm\u0022,\u0022coreBoardLayer3\u0022:\u0022inner Layer\u0022,\u0022coreBoardMaterialType3\u0022:\u0022Copper\u0022,\u0022coreBoardThickness3\u0022:\u00220.0300mm\u0022,\u0022coreBoardRemark\u0022:\u00220.075mm(without copper)\u0022}",
      "contentKey": "impedanceContent_23fac89cbacc4c2ca437027ec1627e16",
      "deleteFlag": false,
      "iaminationType": 3,
      "impedanceIaminationAccessId": "23fac89cbacc4c2ca437027ec1627e16",
      "impedanceIaminationKeyId": 30156,
      "sort": 5
    },
    {
      "content": "{\u0022preLayer\u0022:\u0022Prepreg\u0022,\u0022preMaterialType\u0022:\u00222116\u0022,\u0022preThickness\u0022:\u00220.1120mm\u0022,\u0022coreBoardRemark\u0022:\u0022\u0022}",
      "contentKey": "impedanceContent_6f1dd1bcf37b4d94a70d5c9480a4be1d",
      "deleteFlag": false,
      "iaminationType": 2,
      "impedanceIaminationAccessId": "6f1dd1bcf37b4d94a70d5c9480a4be1d",
      "impedanceIaminationKeyId": 30157,
      "sort": 6
    },
    {
      "content": "{\u0022preLayer\u0022:\u0022Prepreg\u0022,\u0022preMaterialType\u0022:\u00221080\u0022,\u0022preThickness\u0022:\u00220.0860mm\u0022,\u0022coreBoardRemark\u0022:\u0022\u0022}",
      "contentKey": "impedanceContent_d7f658eb85254930b9fdf5c71a33bc3c",
      "deleteFlag": false,
      "iaminationType": 2,
      "impedanceIaminationAccessId": "d7f658eb85254930b9fdf5c71a33bc3c",
      "impedanceIaminationKeyId": 30158,
      "sort": 7
    },
    {
      "content": "{\u0022preLayer\u0022:\u0022Prepreg\u0022,\u0022preMaterialType\u0022:\u00222116\u0022,\u0022preThickness\u0022:\u00220.1120mm\u0022,\u0022coreBoardRemark\u0022:\u0022\u0022}",
      "contentKey": "impedanceContent_cafeadaa44254315a2253805ed1d4096",
      "deleteFlag": false,
      "iaminationType": 2,
      "impedanceIaminationAccessId": "cafeadaa44254315a2253805ed1d4096",
      "impedanceIaminationKeyId": 30159,
      "sort": 8
    },
    {
      "content": "{\u0022coreBoardLayer1\u0022:\u0022inner Layer\u0022,\u0022coreBoardMaterialType1\u0022:\u0022Copper\u0022,\u0022coreBoardThickness1\u0022:\u00220.0300mm\u0022,\u0022coreBoardLayer2\u0022:\u0022Core\u0022,\u0022coreBoardMaterialType2\u0022:\u0022Core\u0022,\u0022coreBoardThickness2\u0022:\u00220.0750mm\u0022,\u0022coreBoardLayer3\u0022:\u0022inner Layer\u0022,\u0022coreBoardMaterialType3\u0022:\u0022Copper\u0022,\u0022coreBoardThickness3\u0022:\u00220.0300mm\u0022,\u0022coreBoardRemark\u0022:\u00220.075mm(without copper)\u0022}",
      "contentKey": "impedanceContent_08016b9d9e894d9d8c1d4026ba70785f",
      "deleteFlag": false,
      "iaminationType": 3,
      "impedanceIaminationAccessId": "08016b9d9e894d9d8c1d4026ba70785f",
      "impedanceIaminationKeyId": 30160,
      "sort": 9
    },
    {
      "content": "{\u0022preLayer\u0022:\u0022Prepreg\u0022,\u0022preMaterialType\u0022:\u00222116\u0022,\u0022preThickness\u0022:\u00220.1120mm\u0022,\u0022coreBoardRemark\u0022:\u0022\u0022}",
      "contentKey": "impedanceContent_70d020ac0e5b4a28bfb245097e8583ca",
      "deleteFlag": false,
      "iaminationType": 2,
      "impedanceIaminationAccessId": "70d020ac0e5b4a28bfb245097e8583ca",
      "impedanceIaminationKeyId": 30161,
      "sort": 10
    },
    {
      "content": "{\u0022preLayer\u0022:\u0022Prepreg\u0022,\u0022preMaterialType\u0022:\u00222116\u0022,\u0022preThickness\u0022:\u00220.1120mm\u0022,\u0022coreBoardRemark\u0022:\u0022\u0022}",
      "contentKey": "impedanceContent_9c7a4668e17d4015a78c837268700bcd",
      "deleteFlag": false,
      "iaminationType": 2,
      "impedanceIaminationAccessId": "9c7a4668e17d4015a78c837268700bcd",
      "impedanceIaminationKeyId": 30162,
      "sort": 11
    },
    {
      "content": "{\u0022coreBoardLayer1\u0022:\u0022inner Layer\u0022,\u0022coreBoardMaterialType1\u0022:\u0022Copper\u0022,\u0022coreBoardThickness1\u0022:\u00220.0300mm\u0022,\u0022coreBoardLayer2\u0022:\u0022Core\u0022,\u0022coreBoardMaterialType2\u0022:\u0022Core\u0022,\u0022coreBoardThickness2\u0022:\u00220.0750mm\u0022,\u0022coreBoardLayer3\u0022:\u0022inner Layer\u0022,\u0022coreBoardMaterialType3\u0022:\u0022Copper\u0022,\u0022coreBoardThickness3\u0022:\u00220.0300mm\u0022,\u0022coreBoardRemark\u0022:\u00220.075mm(without copper)\u0022}",
      "contentKey": "impedanceContent_6419de8730c14b399bcda112e1f02e06",
      "deleteFlag": false,
      "iaminationType": 3,
      "impedanceIaminationAccessId": "6419de8730c14b399bcda112e1f02e06",
      "impedanceIaminationKeyId": 30163,
      "sort": 12
    },
    {
      "content": "{\u0022preLayer\u0022:\u0022Prepreg\u0022,\u0022preMaterialType\u0022:\u00221080\u0022,\u0022preThickness\u0022:\u00220.0710mm\u0022,\u0022coreBoardRemark\u0022:\u0022\u0022}",
      "contentKey": "impedanceContent_dc98b7c123c3413a8bf709d76841d1b5",
      "deleteFlag": false,
      "iaminationType": 2,
      "impedanceIaminationAccessId": "dc98b7c123c3413a8bf709d76841d1b5",
      "impedanceIaminationKeyId": 30164,
      "sort": 13
    },
    {
      "content": "{\u0022LineLayer\u0022:\u0022Layer\u0022,\u0022lineMaterialType\u0022:\u0022Copper\u0022,\u0022LineThickness\u0022:\u00220.0350mm\u0022,\u0022coreBoardRemark\u0022:\u0022\u0022}",
      "contentKey": "impedanceContent_7b8370bfcbdd46f8a04d00c1f5208148",
      "deleteFlag": false,
      "iaminationType": 1,
      "impedanceIaminationAccessId": "7b8370bfcbdd46f8a04d00c1f5208148",
      "impedanceIaminationKeyId": 30165,
      "sort": 14
    }
  ],
  "impedanceTemplateCode": "202410090331382103",
  "laminationType": 2,
  "compressionThickness": 1.51
}