{
  "templateName": "JLC08201H-1080",
  "showName": "JLC08201H-1080",
  "stencilLayer": 8,
  "stencilPly": 2,
  "cuprumThickness": 1,
  "insideCuprumThickness": 0.5,
  "defaultFlag": false,
  "expeditedFlag": false,
  "enableFlag": true,
  "sort": 4,
  "fixedFee": 550,
  "coefficient": 110,
  "iaminationList": [
    {
      "content": "{\u0022LineLayer\u0022:\u0022Layer\u0022,\u0022lineMaterialType\u0022:\u0022Copper\u0022,\u0022LineThickness\u0022:\u00220.035mm\u0022,\u0022coreBoardRemark\u0022:\u0022\u0022}",
      "contentKey": "impedanceContent_33eabd386b6148569768774b464e0c5d",
      "deleteFlag": false,
      "iaminationType": 1,
      "impedanceIaminationAccessId": "33eabd386b6148569768774b464e0c5d",
      "impedanceIaminationKeyId": 1245,
      "sort": 0
    },
    {
      "content": "{\u0022preLayer\u0022:\u0022Prepreg\u0022,\u0022preMaterialType\u0022:\u00221080*1\u0022,\u0022preThickness\u0022:\u00220.0764mm\u0022,\u0022coreBoardRemark\u0022:\u0022\u0022}",
      "contentKey": "impedanceContent_93179e5d426f40c68c4d5e41f49e8431",
      "deleteFlag": false,
      "iaminationType": 2,
      "impedanceIaminationAccessId": "93179e5d426f40c68c4d5e41f49e8431",
      "impedanceIaminationKeyId": 1246,
      "sort": 1
    },
    {
      "content": "{\u0022coreBoardLayer1\u0022:\u0022inner Layer\u0022,\u0022coreBoardMaterialType1\u0022:\u0022Copper\u0022,\u0022coreBoardThickness1\u0022:\u00220.0152mm\u0022,\u0022coreBoardLayer2\u0022:\u0022Core\u0022,\u0022coreBoardMaterialType2\u0022:\u0022Core\u0022,\u0022coreBoardThickness2\u0022:\u00220.4mm\u0022,\u0022coreBoardLayer3\u0022:\u0022inner Layer\u0022,\u0022coreBoardMaterialType3\u0022:\u0022Copper\u0022,\u0022coreBoardThickness3\u0022:\u00220.0152mm\u0022,\u0022coreBoardRemark\u0022:\u00220.4mm (without copper core)\u0022}",
      "contentKey": "impedanceContent_c9df7c0c5819408483d2e7785c7043e0",
      "deleteFlag": false,
      "iaminationType": 3,
      "impedanceIaminationAccessId": "c9df7c0c5819408483d2e7785c7043e0",
      "impedanceIaminationKeyId": 1247,
      "sort": 2
    },
    {
      "content": "{\u0022preLayer\u0022:\u0022Prepreg\u0022,\u0022preMaterialType\u0022:\u00222116*1\u0022,\u0022preThickness\u0022:\u00220.1164mm\u0022,\u0022coreBoardRemark\u0022:\u0022\u0022}",
      "contentKey": "impedanceContent_94316425ecec4533a273613fe08a9297",
      "deleteFlag": false,
      "iaminationType": 2,
      "impedanceIaminationAccessId": "94316425ecec4533a273613fe08a9297",
      "impedanceIaminationKeyId": 1248,
      "sort": 3
    },
    {
      "content": "{\u0022preLayer\u0022:\u0022Prepreg\u0022,\u0022preMaterialType\u0022:\u00222116*1\u0022,\u0022preThickness\u0022:\u00220.1164mm\u0022,\u0022coreBoardRemark\u0022:\u0022\u0022}",
      "contentKey": "impedanceContent_e3a13355a11f4e839584070116cd15e9",
      "deleteFlag": false,
      "iaminationType": 2,
      "impedanceIaminationAccessId": "e3a13355a11f4e839584070116cd15e9",
      "impedanceIaminationKeyId": 1249,
      "sort": 4
    },
    {
      "content": "{\u0022coreBoardLayer1\u0022:\u0022inner Layer\u0022,\u0022coreBoardMaterialType1\u0022:\u0022Copper\u0022,\u0022coreBoardThickness1\u0022:\u00220.0152mm\u0022,\u0022coreBoardLayer2\u0022:\u0022Core\u0022,\u0022coreBoardMaterialType2\u0022:\u0022Core\u0022,\u0022coreBoardThickness2\u0022:\u00220.4mm\u0022,\u0022coreBoardLayer3\u0022:\u0022inner Layer\u0022,\u0022coreBoardMaterialType3\u0022:\u0022Copper\u0022,\u0022coreBoardThickness3\u0022:\u00220.0152mm\u0022,\u0022coreBoardRemark\u0022:\u00220.4mm (without copper core)\u0022}",
      "contentKey": "impedanceContent_ddae3a739cb641468d63e24a19f3cfa8",
      "deleteFlag": false,
      "iaminationType": 3,
      "impedanceIaminationAccessId": "ddae3a739cb641468d63e24a19f3cfa8",
      "impedanceIaminationKeyId": 1250,
      "sort": 5
    },
    {
      "content": "{\u0022preLayer\u0022:\u0022Prepreg\u0022,\u0022preMaterialType\u0022:\u00222116*1\u0022,\u0022preThickness\u0022:\u00220.1164mm\u0022,\u0022coreBoardRemark\u0022:\u0022\u0022}",
      "contentKey": "impedanceContent_9ddeeb99b73c44188c79d0aa7013fb78",
      "deleteFlag": false,
      "iaminationType": 2,
      "impedanceIaminationAccessId": "9ddeeb99b73c44188c79d0aa7013fb78",
      "impedanceIaminationKeyId": 1251,
      "sort": 6
    },
    {
      "content": "{\u0022preLayer\u0022:\u0022Prepreg\u0022,\u0022preMaterialType\u0022:\u00222116*1\u0022,\u0022preThickness\u0022:\u00220.1164mm\u0022,\u0022coreBoardRemark\u0022:\u0022\u0022}",
      "contentKey": "impedanceContent_3f121462a4964a7fb645105ce9d0d440",
      "deleteFlag": false,
      "iaminationType": 2,
      "impedanceIaminationAccessId": "3f121462a4964a7fb645105ce9d0d440",
      "impedanceIaminationKeyId": 1252,
      "sort": 7
    },
    {
      "content": "{\u0022coreBoardLayer1\u0022:\u0022inner Layer\u0022,\u0022coreBoardMaterialType1\u0022:\u0022Copper\u0022,\u0022coreBoardThickness1\u0022:\u00220.0152mm\u0022,\u0022coreBoardLayer2\u0022:\u0022Core\u0022,\u0022coreBoardMaterialType2\u0022:\u0022Core\u0022,\u0022coreBoardThickness2\u0022:\u00220.4mm\u0022,\u0022coreBoardLayer3\u0022:\u0022inner Layer\u0022,\u0022coreBoardMaterialType3\u0022:\u0022Copper\u0022,\u0022coreBoardThickness3\u0022:\u00220.0152mm\u0022,\u0022coreBoardRemark\u0022:\u00220.4mm (without copper core)\u0022}",
      "contentKey": "impedanceContent_7558df53665d4cd7959e6b21935b0566",
      "deleteFlag": false,
      "iaminationType": 3,
      "impedanceIaminationAccessId": "7558df53665d4cd7959e6b21935b0566",
      "impedanceIaminationKeyId": 1253,
      "sort": 8
    },
    {
      "content": "{\u0022preLayer\u0022:\u0022Prepreg\u0022,\u0022preMaterialType\u0022:\u00221080*1\u0022,\u0022preThickness\u0022:\u00220.0764mm\u0022,\u0022coreBoardRemark\u0022:\u0022\u0022}",
      "contentKey": "impedanceContent_5dc95a4efac5462da0b524025012d1ec",
      "deleteFlag": false,
      "iaminationType": 2,
      "impedanceIaminationAccessId": "5dc95a4efac5462da0b524025012d1ec",
      "impedanceIaminationKeyId": 1254,
      "sort": 9
    },
    {
      "content": "{\u0022LineLayer\u0022:\u0022Layer\u0022,\u0022lineMaterialType\u0022:\u0022Copper\u0022,\u0022LineThickness\u0022:\u00220.035mm\u0022,\u0022coreBoardRemark\u0022:\u0022\u0022}",
      "contentKey": "impedanceContent_6a049d08cc9d405781d8eb13fbd832b0",
      "deleteFlag": false,
      "iaminationType": 1,
      "impedanceIaminationAccessId": "6a049d08cc9d405781d8eb13fbd832b0",
      "impedanceIaminationKeyId": 1255,
      "sort": 10
    }
  ],
  "impedanceTemplateCode": "20220415052445",
  "laminationType": 2,
  "compressionThickness": 1.9796
}