{
  "templateName": "JLC122011-2116",
  "showName": "JLC122011-2116",
  "stencilLayer": 12,
  "stencilPly": 2,
  "cuprumThickness": 1,
  "insideCuprumThickness": 1,
  "defaultFlag": false,
  "expeditedFlag": false,
  "enableFlag": true,
  "sort": 2,
  "fixedFee": 0,
  "coefficient": 0,
  "iaminationList": [
    {
      "content": "{\u0022LineLayer\u0022:\u0022Layer\u0022,\u0022lineMaterialType\u0022:\u0022Copper\u0022,\u0022LineThickness\u0022:\u00220.035mm\u0022,\u0022coreBoardRemark\u0022:\u0022\u0022}",
      "contentKey": "impedanceContent_3bf35b0c782649c89143ecebb8765b15",
      "deleteFlag": false,
      "iaminationType": 1,
      "impedanceIaminationAccessId": "3bf35b0c782649c89143ecebb8765b15",
      "impedanceIaminationKeyId": 1677,
      "sort": 0
    },
    {
      "content": "{\u0022preLayer\u0022:\u0022Prepreg\u0022,\u0022preMaterialType\u0022:\u00222116*1\u0022,\u0022preThickness\u0022:\u00220.112mm\u0022,\u0022coreBoardRemark\u0022:\u0022\u0022}",
      "contentKey": "impedanceContent_dd439ead84c9496e83a503acfa8cf8d3",
      "deleteFlag": false,
      "iaminationType": 2,
      "impedanceIaminationAccessId": "dd439ead84c9496e83a503acfa8cf8d3",
      "impedanceIaminationKeyId": 1678,
      "sort": 1
    },
    {
      "content": "{\u0022coreBoardLayer1\u0022:\u0022inner Layer\u0022,\u0022coreBoardMaterialType1\u0022:\u0022Copper\u0022,\u0022coreBoardThickness1\u0022:\u00220.03mm\u0022,\u0022coreBoardLayer2\u0022:\u0022Core\u0022,\u0022coreBoardMaterialType2\u0022:\u0022Core\u0022,\u0022coreBoardThickness2\u0022:\u00220.1mm\u0022,\u0022coreBoardLayer3\u0022:\u0022inner Layer\u0022,\u0022coreBoardMaterialType3\u0022:\u0022Copper\u0022,\u0022coreBoardThickness3\u0022:\u00220.03mm\u0022,\u0022coreBoardRemark\u0022:\u00220.1mm (without copper core)\u0022}",
      "contentKey": "impedanceContent_14c40757b93d4652b790ad86c14b9e1a",
      "deleteFlag": false,
      "iaminationType": 3,
      "impedanceIaminationAccessId": "14c40757b93d4652b790ad86c14b9e1a",
      "impedanceIaminationKeyId": 1679,
      "sort": 2
    },
    {
      "content": "{\u0022preLayer\u0022:\u0022Prepreg\u0022,\u0022preMaterialType\u0022:\u00222116*1\u0022,\u0022preThickness\u0022:\u00220.112mm\u0022,\u0022coreBoardRemark\u0022:\u0022\u0022}",
      "contentKey": "impedanceContent_c8535407b76b4c0a9e0a71762194db0a",
      "deleteFlag": false,
      "iaminationType": 2,
      "impedanceIaminationAccessId": "c8535407b76b4c0a9e0a71762194db0a",
      "impedanceIaminationKeyId": 1680,
      "sort": 3
    },
    {
      "content": "{\u0022preLayer\u0022:\u0022Prepreg\u0022,\u0022preMaterialType\u0022:\u00222116*1\u0022,\u0022preThickness\u0022:\u00220.112mm\u0022,\u0022coreBoardRemark\u0022:\u0022\u0022}",
      "contentKey": "impedanceContent_72199a342af7479ba399c5b719310da4",
      "deleteFlag": false,
      "iaminationType": 2,
      "impedanceIaminationAccessId": "72199a342af7479ba399c5b719310da4",
      "impedanceIaminationKeyId": 1681,
      "sort": 4
    },
    {
      "content": "{\u0022coreBoardLayer1\u0022:\u0022inner Layer\u0022,\u0022coreBoardMaterialType1\u0022:\u0022Copper\u0022,\u0022coreBoardThickness1\u0022:\u00220.03mm\u0022,\u0022coreBoardLayer2\u0022:\u0022Core\u0022,\u0022coreBoardMaterialType2\u0022:\u0022Core\u0022,\u0022coreBoardThickness2\u0022:\u00220.1mm\u0022,\u0022coreBoardLayer3\u0022:\u0022inner Layer\u0022,\u0022coreBoardMaterialType3\u0022:\u0022Copper\u0022,\u0022coreBoardThickness3\u0022:\u00220.03mm\u0022,\u0022coreBoardRemark\u0022:\u00220.1mm (without copper core)\u0022}",
      "contentKey": "impedanceContent_25ab9ac990b94272aab6ee4a475259dc",
      "deleteFlag": false,
      "iaminationType": 3,
      "impedanceIaminationAccessId": "25ab9ac990b94272aab6ee4a475259dc",
      "impedanceIaminationKeyId": 1682,
      "sort": 5
    },
    {
      "content": "{\u0022preLayer\u0022:\u0022Prepreg\u0022,\u0022preMaterialType\u0022:\u00222116*1\u0022,\u0022preThickness\u0022:\u00220.112mm\u0022,\u0022coreBoardRemark\u0022:\u0022\u0022}",
      "contentKey": "impedanceContent_bc09cf365c5145f78dc02c6cf71ccd34",
      "deleteFlag": false,
      "iaminationType": 2,
      "impedanceIaminationAccessId": "bc09cf365c5145f78dc02c6cf71ccd34",
      "impedanceIaminationKeyId": 1683,
      "sort": 6
    },
    {
      "content": "{\u0022preLayer\u0022:\u0022Prepreg\u0022,\u0022preMaterialType\u0022:\u00222116*1\u0022,\u0022preThickness\u0022:\u00220.112mm\u0022,\u0022coreBoardRemark\u0022:\u0022\u0022}",
      "contentKey": "impedanceContent_e579d8ef67ec4689ad8870e104f49a2e",
      "deleteFlag": false,
      "iaminationType": 2,
      "impedanceIaminationAccessId": "e579d8ef67ec4689ad8870e104f49a2e",
      "impedanceIaminationKeyId": 1684,
      "sort": 7
    },
    {
      "content": "{\u0022coreBoardLayer1\u0022:\u0022inner Layer\u0022,\u0022coreBoardMaterialType1\u0022:\u0022Copper\u0022,\u0022coreBoardThickness1\u0022:\u00220.03mm\u0022,\u0022coreBoardLayer2\u0022:\u0022Core\u0022,\u0022coreBoardMaterialType2\u0022:\u0022Core\u0022,\u0022coreBoardThickness2\u0022:\u00220.1mm\u0022,\u0022coreBoardLayer3\u0022:\u0022inner Layer\u0022,\u0022coreBoardMaterialType3\u0022:\u0022Copper\u0022,\u0022coreBoardThickness3\u0022:\u00220.03mm\u0022,\u0022coreBoardRemark\u0022:\u00220.1mm (without copper core)\u0022}",
      "contentKey": "impedanceContent_0f0f16c82799480fb87638533b107ddc",
      "deleteFlag": false,
      "iaminationType": 3,
      "impedanceIaminationAccessId": "0f0f16c82799480fb87638533b107ddc",
      "impedanceIaminationKeyId": 1685,
      "sort": 8
    },
    {
      "content": "{\u0022preLayer\u0022:\u0022Prepreg\u0022,\u0022preMaterialType\u0022:\u00222116*1\u0022,\u0022preThickness\u0022:\u00220.112mm\u0022,\u0022coreBoardRemark\u0022:\u0022\u0022}",
      "contentKey": "impedanceContent_1c49bde59c5242ffb6f90f7cddcdc57e",
      "deleteFlag": false,
      "iaminationType": 2,
      "impedanceIaminationAccessId": "1c49bde59c5242ffb6f90f7cddcdc57e",
      "impedanceIaminationKeyId": 1706,
      "sort": 9
    },
    {
      "content": "{\u0022preLayer\u0022:\u0022Prepreg\u0022,\u0022preMaterialType\u0022:\u00222116*1\u0022,\u0022preThickness\u0022:\u00220.112mm\u0022,\u0022coreBoardRemark\u0022:\u0022\u0022}",
      "contentKey": "impedanceContent_7b10c4dcde784f5fb1b592eb81c9a5e3",
      "deleteFlag": false,
      "iaminationType": 2,
      "impedanceIaminationAccessId": "7b10c4dcde784f5fb1b592eb81c9a5e3",
      "impedanceIaminationKeyId": 1707,
      "sort": 10
    },
    {
      "content": "{\u0022coreBoardLayer1\u0022:\u0022inner Layer\u0022,\u0022coreBoardMaterialType1\u0022:\u0022Copper\u0022,\u0022coreBoardThickness1\u0022:\u00220.03mm\u0022,\u0022coreBoardLayer2\u0022:\u0022Core\u0022,\u0022coreBoardMaterialType2\u0022:\u0022Core\u0022,\u0022coreBoardThickness2\u0022:\u00220.1mm\u0022,\u0022coreBoardLayer3\u0022:\u0022inner Layer\u0022,\u0022coreBoardMaterialType3\u0022:\u0022Copper\u0022,\u0022coreBoardThickness3\u0022:\u00220.03mm\u0022,\u0022coreBoardRemark\u0022:\u00220.1mm (without copper core)\u0022}",
      "contentKey": "impedanceContent_cc5145295b1f40659cdc536cca317a50",
      "deleteFlag": false,
      "iaminationType": 3,
      "impedanceIaminationAccessId": "cc5145295b1f40659cdc536cca317a50",
      "impedanceIaminationKeyId": 1708,
      "sort": 11
    },
    {
      "content": "{\u0022preLayer\u0022:\u0022Prepreg\u0022,\u0022preMaterialType\u0022:\u00222116*1\u0022,\u0022preThickness\u0022:\u00220.112mm\u0022,\u0022coreBoardRemark\u0022:\u0022\u0022}",
      "contentKey": "impedanceContent_0d1d3bcbc73e4fd69a8c07cb5517d169",
      "deleteFlag": false,
      "iaminationType": 2,
      "impedanceIaminationAccessId": "0d1d3bcbc73e4fd69a8c07cb5517d169",
      "impedanceIaminationKeyId": 1709,
      "sort": 12
    },
    {
      "content": "{\u0022preLayer\u0022:\u0022Prepreg\u0022,\u0022preMaterialType\u0022:\u00222116*1\u0022,\u0022preThickness\u0022:\u00220.112mm\u0022,\u0022coreBoardRemark\u0022:\u0022\u0022}",
      "contentKey": "impedanceContent_3766daebc4ed4e72b2f6da76de2be22d",
      "deleteFlag": false,
      "iaminationType": 2,
      "impedanceIaminationAccessId": "3766daebc4ed4e72b2f6da76de2be22d",
      "impedanceIaminationKeyId": 1710,
      "sort": 13
    },
    {
      "content": "{\u0022coreBoardLayer1\u0022:\u0022inner Layer\u0022,\u0022coreBoardMaterialType1\u0022:\u0022Copper\u0022,\u0022coreBoardThickness1\u0022:\u00220.03mm\u0022,\u0022coreBoardLayer2\u0022:\u0022Core\u0022,\u0022coreBoardMaterialType2\u0022:\u0022Core\u0022,\u0022coreBoardThickness2\u0022:\u00220.1mm\u0022,\u0022coreBoardLayer3\u0022:\u0022inner Layer\u0022,\u0022coreBoardMaterialType3\u0022:\u0022Copper\u0022,\u0022coreBoardThickness3\u0022:\u00220.03mm\u0022,\u0022coreBoardRemark\u0022:\u00220.1mm (without copper core)\u0022}",
      "contentKey": "impedanceContent_10a5807fabdc4efe962648593c6b1bb2",
      "deleteFlag": false,
      "iaminationType": 3,
      "impedanceIaminationAccessId": "10a5807fabdc4efe962648593c6b1bb2",
      "impedanceIaminationKeyId": 1711,
      "sort": 14
    },
    {
      "content": "{\u0022preLayer\u0022:\u0022Prepreg\u0022,\u0022preMaterialType\u0022:\u00222116*1\u0022,\u0022preThickness\u0022:\u00220.112mm\u0022,\u0022coreBoardRemark\u0022:\u0022\u0022}",
      "contentKey": "impedanceContent_fcfe58532aa044da8be262604b525e16",
      "deleteFlag": false,
      "iaminationType": 2,
      "impedanceIaminationAccessId": "fcfe58532aa044da8be262604b525e16",
      "impedanceIaminationKeyId": 1712,
      "sort": 15
    },
    {
      "content": "{\u0022LineLayer\u0022:\u0022Layer\u0022,\u0022lineMaterialType\u0022:\u0022Copper\u0022,\u0022LineThickness\u0022:\u00220.035mm\u0022,\u0022coreBoardRemark\u0022:\u0022\u0022}",
      "contentKey": "impedanceContent_441b8e15363f4783b53731b6c335f146",
      "deleteFlag": false,
      "iaminationType": 1,
      "impedanceIaminationAccessId": "441b8e15363f4783b53731b6c335f146",
      "impedanceIaminationKeyId": 1713,
      "sort": 16
    }
  ],
  "impedanceTemplateCode": "20220420034526",
  "laminationType": 1,
  "compressionThickness": 1.99
}